chaser.v
// This is interesting but not quite the assignment 
// Its as simple as having four LEDs and lighting only 1 at a time.
// make the advance slow enough so its clear to the human eye

module chaser (
    input clk,
    input rst_n,
    output reg [3:0] out
);
    reg [31:0] counter;
    reg [31:0] period;

    always @(posedge clk) begin
        if (!rst_n) begin
            out <= 4'b0;
            counter <= 32'b0;
            period <= 32'h000000FF;
        end else begin
            if (counter == period) begin 
                counter <= 32'b0;
                out <= 4'b0;
            end else begin
                if (counter < (period >> 2)) begin out <= 4'b0001; end
                else if (counter < (period >> 1)) begin out <= 4'b0010; end
                else if (counter < ((period >> 1)+(period >> 2))) begin out <= 4'b0100; end
                else begin out <= 4'b1000; end
                counter <= counter + 1'b1;
            end
        end
    end
endmodule

chaser_tb.v
`timescale 1ms/1us

module chaser_tb;

    reg clk;
    reg rst_n;
    wire [3:0] out;
    wire bit1;
    wire bit2;
    wire bit3;
    wire bit4;    

    chaser dut (
        .clk(clk),
        .rst_n(rst_n),
        .out(out)
    );

    assign {bit1, bit2, bit3, bit4} = out;

    initial clk = 1'b0;
    always #5 clk = ~clk;

    initial begin
        $dumpfile("chaser_tb.vcd");
        $dumpvars(0, chaser_tb);

        rst_n = 1'b0;
        #50
        rst_n = 1'b1;
        #50000
        $finish;
    end
endmodule

//module led_chaser (
//    input clk,
//    input rst_n,
//    input [31:0] period,
//    output out1,
//    output out2,
//    output out3,
//    output error
//);

chaser_tb.vcd
$date
	Sun Aug  9 14:21:20 2026
$end
$version
	Questa Altera Starter FPGA Edition Version 2025.2
$end
$timescale
	1us
$end

$scope module chaser_tb $end
$var reg 1 ! clk $end
$var reg 1 " rst_n $end
$var wire 1 # out [3] $end
$var wire 1 $ out [2] $end
$var wire 1 % out [1] $end
$var wire 1 & out [0] $end
$var wire 1 ' bit1 $end
$var wire 1 ( bit2 $end
$var wire 1 ) bit3 $end
$var wire 1 * bit4 $end

$scope module dut $end
$var wire 1 + clk $end
$var wire 1 , rst_n $end
$var reg 4 - out [3:0] $end
$var reg 32 . counter [31:0] $end
$var reg 32 / period [31:0] $end
$upscope $end
$upscope $end
$enddefinitions $end
#0
$dumpvars
0!
0"
bx -
bx .
bx /
x&
x%
x$
x#
x'
x(
x)
x*
0,
0+
$end
#5000
1!
1+
b0 -
b0 .
b11111111 /
0&
0%
0$
0#
0*
0)
0(
0'
#10000
0!
0+
#15000
1!
1+
#20000
0!
0+
#25000
1!
1+
#30000
0!
0+
#35000
1!
1+
#40000
0!
0+
#45000
1!
1+
#50000
1"
0!
1,
0+
#55000
1!
1+
b1 -
b1 .
1&
1*
#60000
0!
0+
#65000
1!
1+
b10 .
#70000
0!
0+
#75000
1!
1+
b11 .
#80000
0!
0+
#85000
1!
1+
b100 .
#90000
0!
0+
#95000
1!
1+
b101 .
#100000
0!
0+
#105000
1!
1+
b110 .
#110000
0!
0+
#115000
1!
1+
b111 .
#120000
0!
0+
#125000
1!
1+
b1000 .
#130000
0!
0+
#135000
1!
1+
b1001 .
#140000
0!
0+
#145000
1!
1+
b1010 .
#150000
0!
0+
#155000
1!
1+
b1011 .
#160000
0!
0+
#165000
1!
1+
b1100 .
#170000
0!
0+
#175000
1!
1+
b1101 .
#180000
0!
0+
#185000
1!
1+
b1110 .
#190000
0!
0+
#195000
1!
1+
b1111 .
#200000
0!
0+
#205000
1!
1+
b10000 .
#210000
0!
0+
#215000
1!
1+
b10001 .
#220000
0!
0+
#225000
1!
1+
b10010 .
#230000
0!
0+
#235000
1!
1+
b10011 .
#240000
0!
0+
#245000
1!
1+
b10100 .
#250000
0!
0+
#255000
1!
1+
b10101 .
#260000
0!
0+
#265000
1!
1+
b10110 .
#270000
0!
0+
#275000
1!
1+
b10111 .
#280000
0!
0+
#285000
1!
1+
b11000 .
#290000
0!
0+
#295000
1!
1+
b11001 .
#300000
0!
0+
#305000
1!
1+
b11010 .
#310000
0!
0+
#315000
1!
1+
b11011 .
#320000
0!
0+
#325000
1!
1+
b11100 .
#330000
0!
0+
#335000
1!
1+
b11101 .
#340000
0!
0+
#345000
1!
1+
b11110 .
#350000
0!
0+
#355000
1!
1+
b11111 .
#360000
0!
0+
#365000
1!
1+
b100000 .
#370000
0!
0+
#375000
1!
1+
b100001 .
#380000
0!
0+
#385000
1!
1+
b100010 .
#390000
0!
0+
#395000
1!
1+
b100011 .
#400000
0!
0+
#405000
1!
1+
b100100 .
#410000
0!
0+
#415000
1!
1+
b100101 .
#420000
0!
0+
#425000
1!
1+
b100110 .
#430000
0!
0+
#435000
1!
1+
b100111 .
#440000
0!
0+
#445000
1!
1+
b101000 .
#450000
0!
0+
#455000
1!
1+
b101001 .
#460000
0!
0+
#465000
1!
1+
b101010 .
#470000
0!
0+
#475000
1!
1+
b101011 .
#480000
0!
0+
#485000
1!
1+
b101100 .
#490000
0!
0+
#495000
1!
1+
b101101 .
#500000
0!
0+
#505000
1!
1+
b101110 .
#510000
0!
0+
#515000
1!
1+
b101111 .
#520000
0!
0+
#525000
1!
1+
b110000 .
#530000
0!
0+
#535000
1!
1+
b110001 .
#540000
0!
0+
#545000
1!
1+
b110010 .
#550000
0!
0+
#555000
1!
1+
b110011 .
#560000
0!
0+
#565000
1!
1+
b110100 .
#570000
0!
0+
#575000
1!
1+
b110101 .
#580000
0!
0+
#585000
1!
1+
b110110 .
#590000
0!
0+
#595000
1!
1+
b110111 .
#600000
0!
0+
#605000
1!
1+
b111000 .
#610000
0!
0+
#615000
1!
1+
b111001 .
#620000
0!
0+
#625000
1!
1+
b111010 .
#630000
0!
0+
#635000
1!
1+
b111011 .
#640000
0!
0+
#645000
1!
1+
b111100 .
#650000
0!
0+
#655000
1!
1+
b111101 .
#660000
0!
0+
#665000
1!
1+
b111110 .
#670000
0!
0+
#675000
1!
1+
b111111 .
#680000
0!
0+
#685000
1!
1+
b10 -
b1000000 .
0&
1%
0*
1)
#690000
0!
0+
#695000
1!
1+
b1000001 .
#700000
0!
0+
#705000
1!
1+
b1000010 .
#710000
0!
0+
#715000
1!
1+
b1000011 .
#720000
0!
0+
#725000
1!
1+
b1000100 .
#730000
0!
0+
#735000
1!
1+
b1000101 .
#740000
0!
0+
#745000
1!
1+
b1000110 .
#750000
0!
0+
#755000
1!
1+
b1000111 .
#760000
0!
0+
#765000
1!
1+
b1001000 .
#770000
0!
0+
#775000
1!
1+
b1001001 .
#780000
0!
0+
#785000
1!
1+
b1001010 .
#790000
0!
0+
#795000
1!
1+
b1001011 .
#800000
0!
0+
#805000
1!
1+
b1001100 .
#810000
0!
0+
#815000
1!
1+
b1001101 .
#820000
0!
0+
#825000
1!
1+
b1001110 .
#830000
0!
0+
#835000
1!
1+
b1001111 .
#840000
0!
0+
#845000
1!
1+
b1010000 .
#850000
0!
0+
#855000
1!
1+
b1010001 .
#860000
0!
0+
#865000
1!
1+
b1010010 .
#870000
0!
0+
#875000
1!
1+
b1010011 .
#880000
0!
0+
#885000
1!
1+
b1010100 .
#890000
0!
0+
#895000
1!
1+
b1010101 .
#900000
0!
0+
#905000
1!
1+
b1010110 .
#910000
0!
0+
#915000
1!
1+
b1010111 .
#920000
0!
0+
#925000
1!
1+
b1011000 .
#930000
0!
0+
#935000
1!
1+
b1011001 .
#940000
0!
0+
#945000
1!
1+
b1011010 .
#950000
0!
0+
#955000
1!
1+
b1011011 .
#960000
0!
0+
#965000
1!
1+
b1011100 .
#970000
0!
0+
#975000
1!
1+
b1011101 .
#980000
0!
0+
#985000
1!
1+
b1011110 .
#990000
0!
0+
#995000
1!
1+
b1011111 .
#1000000
0!
0+
#1005000
1!
1+
b1100000 .
#1010000
0!
0+
#1015000
1!
1+
b1100001 .
#1020000
0!
0+
#1025000
1!
1+
b1100010 .
#1030000
0!
0+
#1035000
1!
1+
b1100011 .
#1040000
0!
0+
#1045000
1!
1+
b1100100 .
#1050000
0!
0+
#1055000
1!
1+
b1100101 .
#1060000
0!
0+
#1065000
1!
1+
b1100110 .
#1070000
0!
0+
#1075000
1!
1+
b1100111 .
#1080000
0!
0+
#1085000
1!
1+
b1101000 .
#1090000
0!
0+
#1095000
1!
1+
b1101001 .
#1100000
0!
0+
#1105000
1!
1+
b1101010 .
#1110000
0!
0+
#1115000
1!
1+
b1101011 .
#1120000
0!
0+
#1125000
1!
1+
b1101100 .
#1130000
0!
0+
#1135000
1!
1+
b1101101 .
#1140000
0!
0+
#1145000
1!
1+
b1101110 .
#1150000
0!
0+
#1155000
1!
1+
b1101111 .
#1160000
0!
0+
#1165000
1!
1+
b1110000 .
#1170000
0!
0+
#1175000
1!
1+
b1110001 .
#1180000
0!
0+
#1185000
1!
1+
b1110010 .
#1190000
0!
0+
#1195000
1!
1+
b1110011 .
#1200000
0!
0+
#1205000
1!
1+
b1110100 .
#1210000
0!
0+
#1215000
1!
1+
b1110101 .
#1220000
0!
0+
#1225000
1!
1+
b1110110 .
#1230000
0!
0+
#1235000
1!
1+
b1110111 .
#1240000
0!
0+
#1245000
1!
1+
b1111000 .
#1250000
0!
0+
#1255000
1!
1+
b1111001 .
#1260000
0!
0+
#1265000
1!
1+
b1111010 .
#1270000
0!
0+
#1275000
1!
1+
b1111011 .
#1280000
0!
0+
#1285000
1!
1+
b1111100 .
#1290000
0!
0+
#1295000
1!
1+
b1111101 .
#1300000
0!
0+
#1305000
1!
1+
b1111110 .
#1310000
0!
0+
#1315000
1!
1+
b1111111 .
#1320000
0!
0+
#1325000
1!
1+
b100 -
b10000000 .
0%
1$
0)
1(
#1330000
0!
0+
#1335000
1!
1+
b10000001 .
#1340000
0!
0+
#1345000
1!
1+
b10000010 .
#1350000
0!
0+
#1355000
1!
1+
b10000011 .
#1360000
0!
0+
#1365000
1!
1+
b10000100 .
#1370000
0!
0+
#1375000
1!
1+
b10000101 .
#1380000
0!
0+
#1385000
1!
1+
b10000110 .
#1390000
0!
0+
#1395000
1!
1+
b10000111 .
#1400000
0!
0+
#1405000
1!
1+
b10001000 .
#1410000
0!
0+
#1415000
1!
1+
b10001001 .
#1420000
0!
0+
#1425000
1!
1+
b10001010 .
#1430000
0!
0+
#1435000
1!
1+
b10001011 .
#1440000
0!
0+
#1445000
1!
1+
b10001100 .
#1450000
0!
0+
#1455000
1!
1+
b10001101 .
#1460000
0!
0+
#1465000
1!
1+
b10001110 .
#1470000
0!
0+
#1475000
1!
1+
b10001111 .
#1480000
0!
0+
#1485000
1!
1+
b10010000 .
#1490000
0!
0+
#1495000
1!
1+
b10010001 .
#1500000
0!
0+
#1505000
1!
1+
b10010010 .
#1510000
0!
0+
#1515000
1!
1+
b10010011 .
#1520000
0!
0+
#1525000
1!
1+
b10010100 .
#1530000
0!
0+
#1535000
1!
1+
b10010101 .
#1540000
0!
0+
#1545000
1!
1+
b10010110 .
#1550000
0!
0+
#1555000
1!
1+
b10010111 .
#1560000
0!
0+
#1565000
1!
1+
b10011000 .
#1570000
0!
0+
#1575000
1!
1+
b10011001 .
#1580000
0!
0+
#1585000
1!
1+
b10011010 .
#1590000
0!
0+
#1595000
1!
1+
b10011011 .
#1600000
0!
0+
#1605000
1!
1+
b10011100 .
#1610000
0!
0+
#1615000
1!
1+
b10011101 .
#1620000
0!
0+
#1625000
1!
1+
b10011110 .
#1630000
0!
0+
#1635000
1!
1+
b10011111 .
#1640000
0!
0+
#1645000
1!
1+
b10100000 .
#1650000
0!
0+
#1655000
1!
1+
b10100001 .
#1660000
0!
0+
#1665000
1!
1+
b10100010 .
#1670000
0!
0+
#1675000
1!
1+
b10100011 .
#1680000
0!
0+
#1685000
1!
1+
b10100100 .
#1690000
0!
0+
#1695000
1!
1+
b10100101 .
#1700000
0!
0+
#1705000
1!
1+
b10100110 .
#1710000
0!
0+
#1715000
1!
1+
b10100111 .
#1720000
0!
0+
#1725000
1!
1+
b10101000 .
#1730000
0!
0+
#1735000
1!
1+
b10101001 .
#1740000
0!
0+
#1745000
1!
1+
b10101010 .
#1750000
0!
0+
#1755000
1!
1+
b10101011 .
#1760000
0!
0+
#1765000
1!
1+
b10101100 .
#1770000
0!
0+
#1775000
1!
1+
b10101101 .
#1780000
0!
0+
#1785000
1!
1+
b10101110 .
#1790000
0!
0+
#1795000
1!
1+
b10101111 .
#1800000
0!
0+
#1805000
1!
1+
b10110000 .
#1810000
0!
0+
#1815000
1!
1+
b10110001 .
#1820000
0!
0+
#1825000
1!
1+
b10110010 .
#1830000
0!
0+
#1835000
1!
1+
b10110011 .
#1840000
0!
0+
#1845000
1!
1+
b10110100 .
#1850000
0!
0+
#1855000
1!
1+
b10110101 .
#1860000
0!
0+
#1865000
1!
1+
b10110110 .
#1870000
0!
0+
#1875000
1!
1+
b10110111 .
#1880000
0!
0+
#1885000
1!
1+
b10111000 .
#1890000
0!
0+
#1895000
1!
1+
b10111001 .
#1900000
0!
0+
#1905000
1!
1+
b10111010 .
#1910000
0!
0+
#1915000
1!
1+
b10111011 .
#1920000
0!
0+
#1925000
1!
1+
b10111100 .
#1930000
0!
0+
#1935000
1!
1+
b10111101 .
#1940000
0!
0+
#1945000
1!
1+
b10111110 .
#1950000
0!
0+
#1955000
1!
1+
b1000 -
b10111111 .
0$
1#
0(
1'
#1960000
0!
0+
#1965000
1!
1+
b11000000 .
#1970000
0!
0+
#1975000
1!
1+
b11000001 .
#1980000
0!
0+
#1985000
1!
1+
b11000010 .
#1990000
0!
0+
#1995000
1!
1+
b11000011 .
#2000000
0!
0+
#2005000
1!
1+
b11000100 .
#2010000
0!
0+
#2015000
1!
1+
b11000101 .
#2020000
0!
0+
#2025000
1!
1+
b11000110 .
#2030000
0!
0+
#2035000
1!
1+
b11000111 .
#2040000
0!
0+
#2045000
1!
1+
b11001000 .
#2050000
0!
0+
#2055000
1!
1+
b11001001 .
#2060000
0!
0+
#2065000
1!
1+
b11001010 .
#2070000
0!
0+
#2075000
1!
1+
b11001011 .
#2080000
0!
0+
#2085000
1!
1+
b11001100 .
#2090000
0!
0+
#2095000
1!
1+
b11001101 .
#2100000
0!
0+
#2105000
1!
1+
b11001110 .
#2110000
0!
0+
#2115000
1!
1+
b11001111 .
#2120000
0!
0+
#2125000
1!
1+
b11010000 .
#2130000
0!
0+
#2135000
1!
1+
b11010001 .
#2140000
0!
0+
#2145000
1!
1+
b11010010 .
#2150000
0!
0+
#2155000
1!
1+
b11010011 .
#2160000
0!
0+
#2165000
1!
1+
b11010100 .
#2170000
0!
0+
#2175000
1!
1+
b11010101 .
#2180000
0!
0+
#2185000
1!
1+
b11010110 .
#2190000
0!
0+
#2195000
1!
1+
b11010111 .
#2200000
0!
0+
#2205000
1!
1+
b11011000 .
#2210000
0!
0+
#2215000
1!
1+
b11011001 .
#2220000
0!
0+
#2225000
1!
1+
b11011010 .
#2230000
0!
0+
#2235000
1!
1+
b11011011 .
#2240000
0!
0+
#2245000
1!
1+
b11011100 .
#2250000
0!
0+
#2255000
1!
1+
b11011101 .
#2260000
0!
0+
#2265000
1!
1+
b11011110 .
#2270000
0!
0+
#2275000
1!
1+
b11011111 .
#2280000
0!
0+
#2285000
1!
1+
b11100000 .
#2290000
0!
0+
#2295000
1!
1+
b11100001 .
#2300000
0!
0+
#2305000
1!
1+
b11100010 .
#2310000
0!
0+
#2315000
1!
1+
b11100011 .
#2320000
0!
0+
#2325000
1!
1+
b11100100 .
#2330000
0!
0+
#2335000
1!
1+
b11100101 .
#2340000
0!
0+
#2345000
1!
1+
b11100110 .
#2350000
0!
0+
#2355000
1!
1+
b11100111 .
#2360000
0!
0+
#2365000
1!
1+
b11101000 .
#2370000
0!
0+
#2375000
1!
1+
b11101001 .
#2380000
0!
0+
#2385000
1!
1+
b11101010 .
#2390000
0!
0+
#2395000
1!
1+
b11101011 .
#2400000
0!
0+
#2405000
1!
1+
b11101100 .
#2410000
0!
0+
#2415000
1!
1+
b11101101 .
#2420000
0!
0+
#2425000
1!
1+
b11101110 .
#2430000
0!
0+
#2435000
1!
1+
b11101111 .
#2440000
0!
0+
#2445000
1!
1+
b11110000 .
#2450000
0!
0+
#2455000
1!
1+
b11110001 .
#2460000
0!
0+
#2465000
1!
1+
b11110010 .
#2470000
0!
0+
#2475000
1!
1+
b11110011 .
#2480000
0!
0+
#2485000
1!
1+
b11110100 .
#2490000
0!
0+
#2495000
1!
1+
b11110101 .
#2500000
0!
0+
#2505000
1!
1+
b11110110 .
#2510000
0!
0+
#2515000
1!
1+
b11110111 .
#2520000
0!
0+
#2525000
1!
1+
b11111000 .
#2530000
0!
0+
#2535000
1!
1+
b11111001 .
#2540000
0!
0+
#2545000
1!
1+
b11111010 .
#2550000
0!
0+
#2555000
1!
1+
b11111011 .
#2560000
0!
0+
#2565000
1!
1+
b11111100 .
#2570000
0!
0+
#2575000
1!
1+
b11111101 .
#2580000
0!
0+
#2585000
1!
1+
b11111110 .
#2590000
0!
0+
#2595000
1!
1+
b11111111 .
#2600000
0!
0+
#2605000
1!
1+
b0 .
b0 -
0#
0'
#2610000
0!
0+
#2615000
1!
1+
b1 -
b1 .
1&
1*
#2620000
0!
0+
#2625000
1!
1+
b10 .
#2630000
0!
0+
#2635000
1!
1+
b11 .
#2640000
0!
0+
#2645000
1!
1+
b100 .
#2650000
0!
0+
#2655000
1!
1+
b101 .
#2660000
0!
0+
#2665000
1!
1+
b110 .
#2670000
0!
0+
#2675000
1!
1+
b111 .
#2680000
0!
0+
#2685000
1!
1+
b1000 .
#2690000
0!
0+
#2695000
1!
1+
b1001 .
#2700000
0!
0+
#2705000
1!
1+
b1010 .
#2710000
0!
0+
#2715000
1!
1+
b1011 .
#2720000
0!
0+
#2725000
1!
1+
b1100 .
#2730000
0!
0+
#2735000
1!
1+
b1101 .
#2740000
0!
0+
#2745000
1!
1+
b1110 .
#2750000
0!
0+
#2755000
1!
1+
b1111 .
#2760000
0!
0+
#2765000
1!
1+
b10000 .
#2770000
0!
0+
#2775000
1!
1+
b10001 .
#2780000
0!
0+
#2785000
1!
1+
b10010 .
#2790000
0!
0+
#2795000
1!
1+
b10011 .
#2800000
0!
0+
#2805000
1!
1+
b10100 .
#2810000
0!
0+
#2815000
1!
1+
b10101 .
#2820000
0!
0+
#2825000
1!
1+
b10110 .
#2830000
0!
0+
#2835000
1!
1+
b10111 .
#2840000
0!
0+
#2845000
1!
1+
b11000 .
#2850000
0!
0+
#2855000
1!
1+
b11001 .
#2860000
0!
0+
#2865000
1!
1+
b11010 .
#2870000
0!
0+
#2875000
1!
1+
b11011 .
#2880000
0!
0+
#2885000
1!
1+
b11100 .
#2890000
0!
0+
#2895000
1!
1+
b11101 .
#2900000
0!
0+
#2905000
1!
1+
b11110 .
#2910000
0!
0+
#2915000
1!
1+
b11111 .
#2920000
0!
0+
#2925000
1!
1+
b100000 .
#2930000
0!
0+
#2935000
1!
1+
b100001 .
#2940000
0!
0+
#2945000
1!
1+
b100010 .
#2950000
0!
0+
#2955000
1!
1+
b100011 .
#2960000
0!
0+
#2965000
1!
1+
b100100 .
#2970000
0!
0+
#2975000
1!
1+
b100101 .
#2980000
0!
0+
#2985000
1!
1+
b100110 .
#2990000
0!
0+
#2995000
1!
1+
b100111 .
#3000000
0!
0+
#3005000
1!
1+
b101000 .
#3010000
0!
0+
#3015000
1!
1+
b101001 .
#3020000
0!
0+
#3025000
1!
1+
b101010 .
#3030000
0!
0+
#3035000
1!
1+
b101011 .
#3040000
0!
0+
#3045000
1!
1+
b101100 .
#3050000
0!
0+
#3055000
1!
1+
b101101 .
#3060000
0!
0+
#3065000
1!
1+
b101110 .
#3070000
0!
0+
#3075000
1!
1+
b101111 .
#3080000
0!
0+
#3085000
1!
1+
b110000 .
#3090000
0!
0+
#3095000
1!
1+
b110001 .
#3100000
0!
0+
#3105000
1!
1+
b110010 .
#3110000
0!
0+
#3115000
1!
1+
b110011 .
#3120000
0!
0+
#3125000
1!
1+
b110100 .
#3130000
0!
0+
#3135000
1!
1+
b110101 .
#3140000
0!
0+
#3145000
1!
1+
b110110 .
#3150000
0!
0+
#3155000
1!
1+
b110111 .
#3160000
0!
0+
#3165000
1!
1+
b111000 .
#3170000
0!
0+
#3175000
1!
1+
b111001 .
#3180000
0!
0+
#3185000
1!
1+
b111010 .
#3190000
0!
0+
#3195000
1!
1+
b111011 .
#3200000
0!
0+
#3205000
1!
1+
b111100 .
#3210000
0!
0+
#3215000
1!
1+
b111101 .
#3220000
0!
0+
#3225000
1!
1+
b111110 .
#3230000
0!
0+
#3235000
1!
1+
b111111 .
#3240000
0!
0+
#3245000
1!
1+
b10 -
b1000000 .
0&
1%
0*
1)
#3250000
0!
0+
#3255000
1!
1+
b1000001 .
#3260000
0!
0+
#3265000
1!
1+
b1000010 .
#3270000
0!
0+
#3275000
1!
1+
b1000011 .
#3280000
0!
0+
#3285000
1!
1+
b1000100 .
#3290000
0!
0+
#3295000
1!
1+
b1000101 .
#3300000
0!
0+
#3305000
1!
1+
b1000110 .
#3310000
0!
0+
#3315000
1!
1+
b1000111 .
#3320000
0!
0+
#3325000
1!
1+
b1001000 .
#3330000
0!
0+
#3335000
1!
1+
b1001001 .
#3340000
0!
0+
#3345000
1!
1+
b1001010 .
#3350000
0!
0+
#3355000
1!
1+
b1001011 .
#3360000
0!
0+
#3365000
1!
1+
b1001100 .
#3370000
0!
0+
#3375000
1!
1+
b1001101 .
#3380000
0!
0+
#3385000
1!
1+
b1001110 .
#3390000
0!
0+
#3395000
1!
1+
b1001111 .
#3400000
0!
0+
#3405000
1!
1+
b1010000 .
#3410000
0!
0+
#3415000
1!
1+
b1010001 .
#3420000
0!
0+
#3425000
1!
1+
b1010010 .
#3430000
0!
0+
#3435000
1!
1+
b1010011 .
#3440000
0!
0+
#3445000
1!
1+
b1010100 .
#3450000
0!
0+
#3455000
1!
1+
b1010101 .
#3460000
0!
0+
#3465000
1!
1+
b1010110 .
#3470000
0!
0+
#3475000
1!
1+
b1010111 .
#3480000
0!
0+
#3485000
1!
1+
b1011000 .
#3490000
0!
0+
#3495000
1!
1+
b1011001 .
#3500000
0!
0+
#3505000
1!
1+
b1011010 .
#3510000
0!
0+
#3515000
1!
1+
b1011011 .
#3520000
0!
0+
#3525000
1!
1+
b1011100 .
#3530000
0!
0+
#3535000
1!
1+
b1011101 .
#3540000
0!
0+
#3545000
1!
1+
b1011110 .
#3550000
0!
0+
#3555000
1!
1+
b1011111 .
#3560000
0!
0+
#3565000
1!
1+
b1100000 .
#3570000
0!
0+
#3575000
1!
1+
b1100001 .
#3580000
0!
0+
#3585000
1!
1+
b1100010 .
#3590000
0!
0+
#3595000
1!
1+
b1100011 .
#3600000
0!
0+
#3605000
1!
1+
b1100100 .
#3610000
0!
0+
#3615000
1!
1+
b1100101 .
#3620000
0!
0+
#3625000
1!
1+
b1100110 .
#3630000
0!
0+
#3635000
1!
1+
b1100111 .
#3640000
0!
0+
#3645000
1!
1+
b1101000 .
#3650000
0!
0+
#3655000
1!
1+
b1101001 .
#3660000
0!
0+
#3665000
1!
1+
b1101010 .
#3670000
0!
0+
#3675000
1!
1+
b1101011 .
#3680000
0!
0+
#3685000
1!
1+
b1101100 .
#3690000
0!
0+
#3695000
1!
1+
b1101101 .
#3700000
0!
0+
#3705000
1!
1+
b1101110 .
#3710000
0!
0+
#3715000
1!
1+
b1101111 .
#3720000
0!
0+
#3725000
1!
1+
b1110000 .
#3730000
0!
0+
#3735000
1!
1+
b1110001 .
#3740000
0!
0+
#3745000
1!
1+
b1110010 .
#3750000
0!
0+
#3755000
1!
1+
b1110011 .
#3760000
0!
0+
#3765000
1!
1+
b1110100 .
#3770000
0!
0+
#3775000
1!
1+
b1110101 .
#3780000
0!
0+
#3785000
1!
1+
b1110110 .
#3790000
0!
0+
#3795000
1!
1+
b1110111 .
#3800000
0!
0+
#3805000
1!
1+
b1111000 .
#3810000
0!
0+
#3815000
1!
1+
b1111001 .
#3820000
0!
0+
#3825000
1!
1+
b1111010 .
#3830000
0!
0+
#3835000
1!
1+
b1111011 .
#3840000
0!
0+
#3845000
1!
1+
b1111100 .
#3850000
0!
0+
#3855000
1!
1+
b1111101 .
#3860000
0!
0+
#3865000
1!
1+
b1111110 .
#3870000
0!
0+
#3875000
1!
1+
b1111111 .
#3880000
0!
0+
#3885000
1!
1+
b100 -
b10000000 .
0%
1$
0)
1(
#3890000
0!
0+
#3895000
1!
1+
b10000001 .
#3900000
0!
0+
#3905000
1!
1+
b10000010 .
#3910000
0!
0+
#3915000
1!
1+
b10000011 .
#3920000
0!
0+
#3925000
1!
1+
b10000100 .
#3930000
0!
0+
#3935000
1!
1+
b10000101 .
#3940000
0!
0+
#3945000
1!
1+
b10000110 .
#3950000
0!
0+
#3955000
1!
1+
b10000111 .
#3960000
0!
0+
#3965000
1!
1+
b10001000 .
#3970000
0!
0+
#3975000
1!
1+
b10001001 .
#3980000
0!
0+
#3985000
1!
1+
b10001010 .
#3990000
0!
0+
#3995000
1!
1+
b10001011 .
#4000000
0!
0+
#4005000
1!
1+
b10001100 .
#4010000
0!
0+
#4015000
1!
1+
b10001101 .
#4020000
0!
0+
#4025000
1!
1+
b10001110 .
#4030000
0!
0+
#4035000
1!
1+
b10001111 .
#4040000
0!
0+
#4045000
1!
1+
b10010000 .
#4050000
0!
0+
#4055000
1!
1+
b10010001 .
#4060000
0!
0+
#4065000
1!
1+
b10010010 .
#4070000
0!
0+
#4075000
1!
1+
b10010011 .
#4080000
0!
0+
#4085000
1!
1+
b10010100 .
#4090000
0!
0+
#4095000
1!
1+
b10010101 .
#4100000
0!
0+
#4105000
1!
1+
b10010110 .
#4110000
0!
0+
#4115000
1!
1+
b10010111 .
#4120000
0!
0+
#4125000
1!
1+
b10011000 .
#4130000
0!
0+
#4135000
1!
1+
b10011001 .
#4140000
0!
0+
#4145000
1!
1+
b10011010 .
#4150000
0!
0+
#4155000
1!
1+
b10011011 .
#4160000
0!
0+
#4165000
1!
1+
b10011100 .
#4170000
0!
0+
#4175000
1!
1+
b10011101 .
#4180000
0!
0+
#4185000
1!
1+
b10011110 .
#4190000
0!
0+
#4195000
1!
1+
b10011111 .
#4200000
0!
0+
#4205000
1!
1+
b10100000 .
#4210000
0!
0+
#4215000
1!
1+
b10100001 .
#4220000
0!
0+
#4225000
1!
1+
b10100010 .
#4230000
0!
0+
#4235000
1!
1+
b10100011 .
#4240000
0!
0+
#4245000
1!
1+
b10100100 .
#4250000
0!
0+
#4255000
1!
1+
b10100101 .
#4260000
0!
0+
#4265000
1!
1+
b10100110 .
#4270000
0!
0+
#4275000
1!
1+
b10100111 .
#4280000
0!
0+
#4285000
1!
1+
b10101000 .
#4290000
0!
0+
#4295000
1!
1+
b10101001 .
#4300000
0!
0+
#4305000
1!
1+
b10101010 .
#4310000
0!
0+
#4315000
1!
1+
b10101011 .
#4320000
0!
0+
#4325000
1!
1+
b10101100 .
#4330000
0!
0+
#4335000
1!
1+
b10101101 .
#4340000
0!
0+
#4345000
1!
1+
b10101110 .
#4350000
0!
0+
#4355000
1!
1+
b10101111 .
#4360000
0!
0+
#4365000
1!
1+
b10110000 .
#4370000
0!
0+
#4375000
1!
1+
b10110001 .
#4380000
0!
0+
#4385000
1!
1+
b10110010 .
#4390000
0!
0+
#4395000
1!
1+
b10110011 .
#4400000
0!
0+
#4405000
1!
1+
b10110100 .
#4410000
0!
0+
#4415000
1!
1+
b10110101 .
#4420000
0!
0+
#4425000
1!
1+
b10110110 .
#4430000
0!
0+
#4435000
1!
1+
b10110111 .
#4440000
0!
0+
#4445000
1!
1+
b10111000 .
#4450000
0!
0+
#4455000
1!
1+
b10111001 .
#4460000
0!
0+
#4465000
1!
1+
b10111010 .
#4470000
0!
0+
#4475000
1!
1+
b10111011 .
#4480000
0!
0+
#4485000
1!
1+
b10111100 .
#4490000
0!
0+
#4495000
1!
1+
b10111101 .
#4500000
0!
0+
#4505000
1!
1+
b10111110 .
#4510000
0!
0+
#4515000
1!
1+
b1000 -
b10111111 .
0$
1#
0(
1'
#4520000
0!
0+
#4525000
1!
1+
b11000000 .
#4530000
0!
0+
#4535000
1!
1+
b11000001 .
#4540000
0!
0+
#4545000
1!
1+
b11000010 .
#4550000
0!
0+
#4555000
1!
1+
b11000011 .
#4560000
0!
0+
#4565000
1!
1+
b11000100 .
#4570000
0!
0+
#4575000
1!
1+
b11000101 .
#4580000
0!
0+
#4585000
1!
1+
b11000110 .
#4590000
0!
0+
#4595000
1!
1+
b11000111 .
#4600000
0!
0+
#4605000
1!
1+
b11001000 .
#4610000
0!
0+
#4615000
1!
1+
b11001001 .
#4620000
0!
0+
#4625000
1!
1+
b11001010 .
#4630000
0!
0+
#4635000
1!
1+
b11001011 .
#4640000
0!
0+
#4645000
1!
1+
b11001100 .
#4650000
0!
0+
#4655000
1!
1+
b11001101 .
#4660000
0!
0+
#4665000
1!
1+
b11001110 .
#4670000
0!
0+
#4675000
1!
1+
b11001111 .
#4680000
0!
0+
#4685000
1!
1+
b11010000 .
#4690000
0!
0+
#4695000
1!
1+
b11010001 .
#4700000
0!
0+
#4705000
1!
1+
b11010010 .
#4710000
0!
0+
#4715000
1!
1+
b11010011 .
#4720000
0!
0+
#4725000
1!
1+
b11010100 .
#4730000
0!
0+
#4735000
1!
1+
b11010101 .
#4740000
0!
0+
#4745000
1!
1+
b11010110 .
#4750000
0!
0+
#4755000
1!
1+
b11010111 .
#4760000
0!
0+
#4765000
1!
1+
b11011000 .
#4770000
0!
0+
#4775000
1!
1+
b11011001 .
#4780000
0!
0+
#4785000
1!
1+
b11011010 .
#4790000
0!
0+
#4795000
1!
1+
b11011011 .
#4800000
0!
0+
#4805000
1!
1+
b11011100 .
#4810000
0!
0+
#4815000
1!
1+
b11011101 .
#4820000
0!
0+
#4825000
1!
1+
b11011110 .
#4830000
0!
0+
#4835000
1!
1+
b11011111 .
#4840000
0!
0+
#4845000
1!
1+
b11100000 .
