PWM_LED_Chaser/PWM_LED_Chaser.srcs/sources_1/imports/PWM_LED_Chaser/pwm_generator.v
module pwm_generator #(
	//parameter DUTYCYCLE = 70, //MUST BE an Integer between 0 and the period
	parameter PERIOD = 1000 //MUST BE AN INTEGER GREATER THAN 1. Is number of base clk cycles in a period
)(
	input clk,
	input rst_n,
	input [31:0] duty,
	output reg out,
	output reg error
);
	// Runs once at time 0 in simulation, before any clock edge.
	// PERIOD is a parameter, so this condition is fully determined
	// at elaboration — the check costs zero hardware.
	initial begin
		if (PERIOD < 2) begin
			// %m expands to the full hierarchical instance path, so you
			// find out *which* instantiation was misparameterised.
			// %0d prints the integer with no padding.
			$display("%m: PERIOD must be >= 2, got %0d", PERIOD);
			$finish;
		end
	end

	reg [31:0] counter;
	reg [31:0] duty_D;

	always @(posedge clk) begin
		if (!rst_n) begin
			out <= 1'b0;
			error <= 1'b0;
			counter <= 32'b0;
			duty_D <= 0;
		end else begin
			if (duty_D>PERIOD) begin
				error <= 1'b1;
			end else begin
				error <= 1'b0;
			end

			if (counter == PERIOD - 1) begin
				duty_D <= duty;
				counter <= 32'b0;
			end else begin
				counter <= counter + 1'b1;
			end
			if (counter>=duty_D) begin	
					out <= 1'b0;
			end else begin
				out <= 1'b1;
			end
		end
	end
endmodule

fader.v
//32'd100 is still hardcoded while pwm_generator #() takes PERIOD as a parameter. 
//They agree only because you left the default at 100. Change PERIOD and the fader 
//silently ramps to the wrong ceiling. Make it one shared parameter passed to both —
// this is the constraint about parameterizing timing constants.

//counter == period should be >=. period is an input port, not a parameter. If it 
// drops while counter is already past the new value, you miss the match and stall 
//for 2³² cycles.

//init is unvalidated. The comment says 0–100, nothing enforces it. Feed it 150 and
// the up-ramp never hits == 100, so duty climbs to 4 billion and wraps. The PWM's 
//error will fire, so you'd notice — but the fader itself has no opinion, and error is
// still a bare passthrough.

//Minor: both endpoints are held for two step-periods, since the turnaround cycle flips up without moving duty. Fine if deliberate, worth a comment either way.
//R2 risk: 100 linear steps. The 0→1 step is a doubling of brightness, the 99→100 step is a 1% change. That's the stair-stepping the requirement calls out.
//Fix 1 and 2 before you put it on hardware.







module fader (
    input clk,
    input rst_n,
    input [31:0] period,
    input [31:0] init, // number between 32'd0 and 32'd100
    output out,
    output error
);

    reg [31:0] duty;
    reg [31:0] counter;
    reg up;

    pwm_generator #() PWM(
        .clk(clk),
	    .rst_n(rst_n),
	    .duty(duty),
	    .out(out),
	    .error(error)
    );

    always @(posedge clk) begin
        if (!rst_n) begin
            duty <= init;
            counter <= 32'b0;
            up <= 1'b1;
        end else begin 
            if (counter == period) begin
                if (up) begin
                    if (duty == 32'd100) begin
                        up <= 1'b0;
                    end else begin 
                        duty <= duty + 32'd1;
                    end
                end else begin
                    if (duty == 32'd0) begin
                        up <= 1'b1;
                    end else begin 
                        duty <= duty - 32'd1;
                    end
                end
                counter <= 32'b0;
            end else begin
                counter <= counter + 1'b1;
            end
        end
    end
endmodule

chaser.v
// This is interesting but not quite the assignment 
// Its as simple as having four LEDs and lighting only 1 at a time.
// make the advance slow enough so its clear to the human eye

module chaser (
    input clk,
    input rst_n,
    input [31:0] period,
    output out1,
    output out2,
    output out3,
    output error
);

    wire err1;
    wire err2;
    wire err3;

    reg [31:0] init1 = 32'd0;
    reg [31:0] init2 = 32'd50;
    reg [31:0] init3 = 32'd100;
    
    assign error = (err1 | err2 | err3);

    fader led_1 (
        .clk(clk),
        .rst_n(rst_n),
        .period(period),
        .init(init1), // number between 32'd0 and 32'd100
        .out(out1),
        .error(err1)
    );
    fader led_2 (
        .clk(clk),
        .rst_n(rst_n),
        .period(period),
        .init(init2), // number between 32'd0 and 32'd100
        .out(out2),
        .error(err2)
    );

    fader led_3 (
        .clk(clk),
        .rst_n(rst_n),
        .period(period),
        .init(init3), // number between 32'd0 and 32'd100
        .out(out3),
        .error(err3)
    );

endmodule

chaser_tb.v
`timescale 1ms/1us

module chaser_tb;

    reg clk;
    reg rst_n;
    reg [31:0] period;
    wire out1;
    wire out2;
    wire out3;
    wire error;

    chaser dut (
        .clk(clk),
        .rst_n(rst_n),
        .period(period),
        .out1(out1),
        .out2(out2),
        .out3(out3),
        .error(error)
    );

    initial clk = 1'b0;
    always #5 clk = ~clk;

    initial begin
        $dumpfile("chaser_tb.vcd");
        $dumpvars(0, chaser_tb);

        rst_n = 1'b0;
        period = 32'h00000000;
        #50
        rst_n = 1'b1;
        period = 32'h0000000F;
        #50000
        $finish;
    end
endmodule

//module led_chaser (
//    input clk,
//    input rst_n,
//    input [31:0] period,
//    output out1,
//    output out2,
//    output out3,
//    output error
//);

chaser_tb.vcd
$date
	Wed Aug  5 22:51:40 2026
$end
$version
	Questa Altera Starter FPGA Edition Version 2025.2
$end
$timescale
	1us
$end

$scope module chaser_tb $end
$var reg 1 ! clk $end
$var reg 1 " rst_n $end
$var reg 32 # period [31:0] $end
$var wire 1 $ out1 $end
$var wire 1 % out2 $end
$var wire 1 & out3 $end
$var wire 1 ' error $end

$scope module dut $end
$var wire 1 ( clk $end
$var wire 1 ) rst_n $end
$var wire 1 * period [31] $end
$var wire 1 + period [30] $end
$var wire 1 , period [29] $end
$var wire 1 - period [28] $end
$var wire 1 . period [27] $end
$var wire 1 / period [26] $end
$var wire 1 0 period [25] $end
$var wire 1 1 period [24] $end
$var wire 1 2 period [23] $end
$var wire 1 3 period [22] $end
$var wire 1 4 period [21] $end
$var wire 1 5 period [20] $end
$var wire 1 6 period [19] $end
$var wire 1 7 period [18] $end
$var wire 1 8 period [17] $end
$var wire 1 9 period [16] $end
$var wire 1 : period [15] $end
$var wire 1 ; period [14] $end
$var wire 1 < period [13] $end
$var wire 1 = period [12] $end
$var wire 1 > period [11] $end
$var wire 1 ? period [10] $end
$var wire 1 @ period [9] $end
$var wire 1 A period [8] $end
$var wire 1 B period [7] $end
$var wire 1 C period [6] $end
$var wire 1 D period [5] $end
$var wire 1 E period [4] $end
$var wire 1 F period [3] $end
$var wire 1 G period [2] $end
$var wire 1 H period [1] $end
$var wire 1 I period [0] $end
$var wire 1 $ out1 $end
$var wire 1 % out2 $end
$var wire 1 & out3 $end
$var wire 1 ' error $end
$var wire 1 J err1 $end
$var wire 1 K err2 $end
$var wire 1 L err3 $end
$var reg 32 M init1 [31:0] $end
$var reg 32 N init2 [31:0] $end
$var reg 32 O init3 [31:0] $end

$scope module led_1 $end
$var wire 1 ( clk $end
$var wire 1 ) rst_n $end
$var wire 1 * period [31] $end
$var wire 1 + period [30] $end
$var wire 1 , period [29] $end
$var wire 1 - period [28] $end
$var wire 1 . period [27] $end
$var wire 1 / period [26] $end
$var wire 1 0 period [25] $end
$var wire 1 1 period [24] $end
$var wire 1 2 period [23] $end
$var wire 1 3 period [22] $end
$var wire 1 4 period [21] $end
$var wire 1 5 period [20] $end
$var wire 1 6 period [19] $end
$var wire 1 7 period [18] $end
$var wire 1 8 period [17] $end
$var wire 1 9 period [16] $end
$var wire 1 : period [15] $end
$var wire 1 ; period [14] $end
$var wire 1 < period [13] $end
$var wire 1 = period [12] $end
$var wire 1 > period [11] $end
$var wire 1 ? period [10] $end
$var wire 1 @ period [9] $end
$var wire 1 A period [8] $end
$var wire 1 B period [7] $end
$var wire 1 C period [6] $end
$var wire 1 D period [5] $end
$var wire 1 E period [4] $end
$var wire 1 F period [3] $end
$var wire 1 G period [2] $end
$var wire 1 H period [1] $end
$var wire 1 I period [0] $end
$var wire 1 P init [31] $end
$var wire 1 Q init [30] $end
$var wire 1 R init [29] $end
$var wire 1 S init [28] $end
$var wire 1 T init [27] $end
$var wire 1 U init [26] $end
$var wire 1 V init [25] $end
$var wire 1 W init [24] $end
$var wire 1 X init [23] $end
$var wire 1 Y init [22] $end
$var wire 1 Z init [21] $end
$var wire 1 [ init [20] $end
$var wire 1 \ init [19] $end
$var wire 1 ] init [18] $end
$var wire 1 ^ init [17] $end
$var wire 1 _ init [16] $end
$var wire 1 ` init [15] $end
$var wire 1 a init [14] $end
$var wire 1 b init [13] $end
$var wire 1 c init [12] $end
$var wire 1 d init [11] $end
$var wire 1 e init [10] $end
$var wire 1 f init [9] $end
$var wire 1 g init [8] $end
$var wire 1 h init [7] $end
$var wire 1 i init [6] $end
$var wire 1 j init [5] $end
$var wire 1 k init [4] $end
$var wire 1 l init [3] $end
$var wire 1 m init [2] $end
$var wire 1 n init [1] $end
$var wire 1 o init [0] $end
$var wire 1 $ out $end
$var wire 1 J error $end
$var reg 32 p duty [31:0] $end
$var reg 32 q counter [31:0] $end
$var reg 1 r up $end

$scope module PWM $end
$var parameter 32 s PERIOD $end
$var wire 1 ( clk $end
$var wire 1 ) rst_n $end
$var wire 1 t duty [31] $end
$var wire 1 u duty [30] $end
$var wire 1 v duty [29] $end
$var wire 1 w duty [28] $end
$var wire 1 x duty [27] $end
$var wire 1 y duty [26] $end
$var wire 1 z duty [25] $end
$var wire 1 { duty [24] $end
$var wire 1 | duty [23] $end
$var wire 1 } duty [22] $end
$var wire 1 ~ duty [21] $end
$var wire 1 !! duty [20] $end
$var wire 1 "! duty [19] $end
$var wire 1 #! duty [18] $end
$var wire 1 $! duty [17] $end
$var wire 1 %! duty [16] $end
$var wire 1 &! duty [15] $end
$var wire 1 '! duty [14] $end
$var wire 1 (! duty [13] $end
$var wire 1 )! duty [12] $end
$var wire 1 *! duty [11] $end
$var wire 1 +! duty [10] $end
$var wire 1 ,! duty [9] $end
$var wire 1 -! duty [8] $end
$var wire 1 .! duty [7] $end
$var wire 1 /! duty [6] $end
$var wire 1 0! duty [5] $end
$var wire 1 1! duty [4] $end
$var wire 1 2! duty [3] $end
$var wire 1 3! duty [2] $end
$var wire 1 4! duty [1] $end
$var wire 1 5! duty [0] $end
$var reg 1 6! out $end
$var reg 1 7! error $end
$var reg 32 8! counter [31:0] $end
$var reg 32 9! duty_D [31:0] $end
$upscope $end
$upscope $end

$scope module led_2 $end
$var wire 1 ( clk $end
$var wire 1 ) rst_n $end
$var wire 1 * period [31] $end
$var wire 1 + period [30] $end
$var wire 1 , period [29] $end
$var wire 1 - period [28] $end
$var wire 1 . period [27] $end
$var wire 1 / period [26] $end
$var wire 1 0 period [25] $end
$var wire 1 1 period [24] $end
$var wire 1 2 period [23] $end
$var wire 1 3 period [22] $end
$var wire 1 4 period [21] $end
$var wire 1 5 period [20] $end
$var wire 1 6 period [19] $end
$var wire 1 7 period [18] $end
$var wire 1 8 period [17] $end
$var wire 1 9 period [16] $end
$var wire 1 : period [15] $end
$var wire 1 ; period [14] $end
$var wire 1 < period [13] $end
$var wire 1 = period [12] $end
$var wire 1 > period [11] $end
$var wire 1 ? period [10] $end
$var wire 1 @ period [9] $end
$var wire 1 A period [8] $end
$var wire 1 B period [7] $end
$var wire 1 C period [6] $end
$var wire 1 D period [5] $end
$var wire 1 E period [4] $end
$var wire 1 F period [3] $end
$var wire 1 G period [2] $end
$var wire 1 H period [1] $end
$var wire 1 I period [0] $end
$var wire 1 :! init [31] $end
$var wire 1 ;! init [30] $end
$var wire 1 <! init [29] $end
$var wire 1 =! init [28] $end
$var wire 1 >! init [27] $end
$var wire 1 ?! init [26] $end
$var wire 1 @! init [25] $end
$var wire 1 A! init [24] $end
$var wire 1 B! init [23] $end
$var wire 1 C! init [22] $end
$var wire 1 D! init [21] $end
$var wire 1 E! init [20] $end
$var wire 1 F! init [19] $end
$var wire 1 G! init [18] $end
$var wire 1 H! init [17] $end
$var wire 1 I! init [16] $end
$var wire 1 J! init [15] $end
$var wire 1 K! init [14] $end
$var wire 1 L! init [13] $end
$var wire 1 M! init [12] $end
$var wire 1 N! init [11] $end
$var wire 1 O! init [10] $end
$var wire 1 P! init [9] $end
$var wire 1 Q! init [8] $end
$var wire 1 R! init [7] $end
$var wire 1 S! init [6] $end
$var wire 1 T! init [5] $end
$var wire 1 U! init [4] $end
$var wire 1 V! init [3] $end
$var wire 1 W! init [2] $end
$var wire 1 X! init [1] $end
$var wire 1 Y! init [0] $end
$var wire 1 % out $end
$var wire 1 K error $end
$var reg 32 Z! duty [31:0] $end
$var reg 32 [! counter [31:0] $end
$var reg 1 \! up $end

$scope module PWM $end
$var parameter 32 ]! PERIOD $end
$var wire 1 ( clk $end
$var wire 1 ) rst_n $end
$var wire 1 ^! duty [31] $end
$var wire 1 _! duty [30] $end
$var wire 1 `! duty [29] $end
$var wire 1 a! duty [28] $end
$var wire 1 b! duty [27] $end
$var wire 1 c! duty [26] $end
$var wire 1 d! duty [25] $end
$var wire 1 e! duty [24] $end
$var wire 1 f! duty [23] $end
$var wire 1 g! duty [22] $end
$var wire 1 h! duty [21] $end
$var wire 1 i! duty [20] $end
$var wire 1 j! duty [19] $end
$var wire 1 k! duty [18] $end
$var wire 1 l! duty [17] $end
$var wire 1 m! duty [16] $end
$var wire 1 n! duty [15] $end
$var wire 1 o! duty [14] $end
$var wire 1 p! duty [13] $end
$var wire 1 q! duty [12] $end
$var wire 1 r! duty [11] $end
$var wire 1 s! duty [10] $end
$var wire 1 t! duty [9] $end
$var wire 1 u! duty [8] $end
$var wire 1 v! duty [7] $end
$var wire 1 w! duty [6] $end
$var wire 1 x! duty [5] $end
$var wire 1 y! duty [4] $end
$var wire 1 z! duty [3] $end
$var wire 1 {! duty [2] $end
$var wire 1 |! duty [1] $end
$var wire 1 }! duty [0] $end
$var reg 1 ~! out $end
$var reg 1 !" error $end
$var reg 32 "" counter [31:0] $end
$var reg 32 #" duty_D [31:0] $end
$upscope $end
$upscope $end

$scope module led_3 $end
$var wire 1 ( clk $end
$var wire 1 ) rst_n $end
$var wire 1 * period [31] $end
$var wire 1 + period [30] $end
$var wire 1 , period [29] $end
$var wire 1 - period [28] $end
$var wire 1 . period [27] $end
$var wire 1 / period [26] $end
$var wire 1 0 period [25] $end
$var wire 1 1 period [24] $end
$var wire 1 2 period [23] $end
$var wire 1 3 period [22] $end
$var wire 1 4 period [21] $end
$var wire 1 5 period [20] $end
$var wire 1 6 period [19] $end
$var wire 1 7 period [18] $end
$var wire 1 8 period [17] $end
$var wire 1 9 period [16] $end
$var wire 1 : period [15] $end
$var wire 1 ; period [14] $end
$var wire 1 < period [13] $end
$var wire 1 = period [12] $end
$var wire 1 > period [11] $end
$var wire 1 ? period [10] $end
$var wire 1 @ period [9] $end
$var wire 1 A period [8] $end
$var wire 1 B period [7] $end
$var wire 1 C period [6] $end
$var wire 1 D period [5] $end
$var wire 1 E period [4] $end
$var wire 1 F period [3] $end
$var wire 1 G period [2] $end
$var wire 1 H period [1] $end
$var wire 1 I period [0] $end
$var wire 1 $" init [31] $end
$var wire 1 %" init [30] $end
$var wire 1 &" init [29] $end
$var wire 1 '" init [28] $end
$var wire 1 (" init [27] $end
$var wire 1 )" init [26] $end
$var wire 1 *" init [25] $end
$var wire 1 +" init [24] $end
$var wire 1 ," init [23] $end
$var wire 1 -" init [22] $end
$var wire 1 ." init [21] $end
$var wire 1 /" init [20] $end
$var wire 1 0" init [19] $end
$var wire 1 1" init [18] $end
$var wire 1 2" init [17] $end
$var wire 1 3" init [16] $end
$var wire 1 4" init [15] $end
$var wire 1 5" init [14] $end
$var wire 1 6" init [13] $end
$var wire 1 7" init [12] $end
$var wire 1 8" init [11] $end
$var wire 1 9" init [10] $end
$var wire 1 :" init [9] $end
$var wire 1 ;" init [8] $end
$var wire 1 <" init [7] $end
$var wire 1 =" init [6] $end
$var wire 1 >" init [5] $end
$var wire 1 ?" init [4] $end
$var wire 1 @" init [3] $end
$var wire 1 A" init [2] $end
$var wire 1 B" init [1] $end
$var wire 1 C" init [0] $end
$var wire 1 & out $end
$var wire 1 L error $end
$var reg 32 D" duty [31:0] $end
$var reg 32 E" counter [31:0] $end
$var reg 1 F" up $end

$scope module PWM $end
$var parameter 32 G" PERIOD $end
$var wire 1 ( clk $end
$var wire 1 ) rst_n $end
$var wire 1 H" duty [31] $end
$var wire 1 I" duty [30] $end
$var wire 1 J" duty [29] $end
$var wire 1 K" duty [28] $end
$var wire 1 L" duty [27] $end
$var wire 1 M" duty [26] $end
$var wire 1 N" duty [25] $end
$var wire 1 O" duty [24] $end
$var wire 1 P" duty [23] $end
$var wire 1 Q" duty [22] $end
$var wire 1 R" duty [21] $end
$var wire 1 S" duty [20] $end
$var wire 1 T" duty [19] $end
$var wire 1 U" duty [18] $end
$var wire 1 V" duty [17] $end
$var wire 1 W" duty [16] $end
$var wire 1 X" duty [15] $end
$var wire 1 Y" duty [14] $end
$var wire 1 Z" duty [13] $end
$var wire 1 [" duty [12] $end
$var wire 1 \" duty [11] $end
$var wire 1 ]" duty [10] $end
$var wire 1 ^" duty [9] $end
$var wire 1 _" duty [8] $end
$var wire 1 `" duty [7] $end
$var wire 1 a" duty [6] $end
$var wire 1 b" duty [5] $end
$var wire 1 c" duty [4] $end
$var wire 1 d" duty [3] $end
$var wire 1 e" duty [2] $end
$var wire 1 f" duty [1] $end
$var wire 1 g" duty [0] $end
$var reg 1 h" out $end
$var reg 1 i" error $end
$var reg 32 j" counter [31:0] $end
$var reg 32 k" duty_D [31:0] $end
$upscope $end
$upscope $end
$upscope $end
$upscope $end
$enddefinitions $end
#0
$dumpvars
0!
0"
b0 #
b0 M
b110010 N
b1100100 O
bx p
bx q
xr
x6!
x7!
bx 8!
bx 9!
bx Z!
bx [!
x\!
x~!
x!"
bx ""
bx #"
bx D"
bx E"
xF"
xh"
xi"
bx j"
bx k"
b1100100 s
b1100100 ]!
b1100100 G"
x$
x%
x&
x'
xJ
xK
xL
0I
0H
0G
0F
0E
0D
0C
0B
0A
0@
0?
0>
0=
0<
0;
0:
09
08
07
06
05
04
03
02
01
00
0/
0.
0-
0,
0+
0*
0)
0(
0C"
0B"
1A"
0@"
0?"
1>"
1="
0<"
0;"
0:"
09"
08"
07"
06"
05"
04"
03"
02"
01"
00"
0/"
0."
0-"
0,"
0+"
0*"
0)"
0("
0'"
0&"
0%"
0$"
0Y!
1X!
0W!
0V!
1U!
1T!
0S!
0R!
0Q!
0P!
0O!
0N!
0M!
0L!
0K!
0J!
0I!
0H!
0G!
0F!
0E!
0D!
0C!
0B!
0A!
0@!
0?!
0>!
0=!
0<!
0;!
0:!
0o
0n
0m
0l
0k
0j
0i
0h
0g
0f
0e
0d
0c
0b
0a
0`
0_
0^
0]
0\
0[
0Z
0Y
0X
0W
0V
0U
0T
0S
0R
0Q
0P
x5!
x4!
x3!
x2!
x1!
x0!
x/!
x.!
x-!
x,!
x+!
x*!
x)!
x(!
x'!
x&!
x%!
x$!
x#!
x"!
x!!
x~
x}
x|
x{
xz
xy
xx
xw
xv
xu
xt
x}!
x|!
x{!
xz!
xy!
xx!
xw!
xv!
xu!
xt!
xs!
xr!
xq!
xp!
xo!
xn!
xm!
xl!
xk!
xj!
xi!
xh!
xg!
xf!
xe!
xd!
xc!
xb!
xa!
x`!
x_!
x^!
xg"
xf"
xe"
xd"
xc"
xb"
xa"
x`"
x_"
x^"
x]"
x\"
x["
xZ"
xY"
xX"
xW"
xV"
xU"
xT"
xS"
xR"
xQ"
xP"
xO"
xN"
xM"
xL"
xK"
xJ"
xI"
xH"
$end
#5000
1!
1(
06!
07!
b0 8!
b0 9!
b0 p
b0 q
1r
0~!
0!"
b0 ""
b0 #"
b110010 Z!
b0 [!
1\!
0h"
0i"
b0 j"
b0 k"
b1100100 D"
b0 E"
1F"
0$
0J
0%
0K
0&
0L
0g"
0f"
1e"
0d"
0c"
1b"
1a"
0`"
0_"
0^"
0]"
0\"
0["
0Z"
0Y"
0X"
0W"
0V"
0U"
0T"
0S"
0R"
0Q"
0P"
0O"
0N"
0M"
0L"
0K"
0J"
0I"
0H"
0}!
1|!
0{!
0z!
1y!
1x!
0w!
0v!
0u!
0t!
0s!
0r!
0q!
0p!
0o!
0n!
0m!
0l!
0k!
0j!
0i!
0h!
0g!
0f!
0e!
0d!
0c!
0b!
0a!
0`!
0_!
0^!
05!
04!
03!
02!
01!
00!
0/!
0.!
0-!
0,!
0+!
0*!
0)!
0(!
0'!
0&!
0%!
0$!
0#!
0"!
0!!
0~
0}
0|
0{
0z
0y
0x
0w
0v
0u
0t
0'
#10000
0!
0(
#15000
1!
1(
#20000
0!
0(
#25000
1!
1(
#30000
0!
0(
#35000
1!
1(
#40000
0!
0(
#45000
1!
1(
#50000
1"
b1111 #
0!
1)
1I
1H
1G
1F
0(
#55000
1!
1(
b1 8!
b1 q
b1 ""
b1 [!
b1 j"
b1 E"
#60000
0!
0(
#65000
1!
1(
b10 E"
b10 j"
b10 [!
b10 ""
b10 q
b10 8!
#70000
0!
0(
#75000
1!
1(
b11 8!
b11 q
b11 ""
b11 [!
b11 j"
b11 E"
#80000
0!
0(
#85000
1!
1(
b100 E"
b100 j"
b100 [!
b100 ""
b100 q
b100 8!
#90000
0!
0(
#95000
1!
1(
b101 8!
b101 q
b101 ""
b101 [!
b101 j"
b101 E"
#100000
0!
0(
#105000
1!
1(
b110 E"
b110 j"
b110 [!
b110 ""
b110 q
b110 8!
#110000
0!
0(
#115000
1!
1(
b111 8!
b111 q
b111 ""
b111 [!
b111 j"
b111 E"
#120000
0!
0(
#125000
1!
1(
b1000 E"
b1000 j"
b1000 [!
b1000 ""
b1000 q
b1000 8!
#130000
0!
0(
#135000
1!
1(
b1001 8!
b1001 q
b1001 ""
b1001 [!
b1001 j"
b1001 E"
#140000
0!
0(
#145000
1!
1(
b1010 E"
b1010 j"
b1010 [!
b1010 ""
b1010 q
b1010 8!
#150000
0!
0(
#155000
1!
1(
b1011 8!
b1011 q
b1011 ""
b1011 [!
b1011 j"
b1011 E"
#160000
0!
0(
#165000
1!
1(
b1100 E"
b1100 j"
b1100 [!
b1100 ""
b1100 q
b1100 8!
#170000
0!
0(
#175000
1!
1(
b1101 8!
b1101 q
b1101 ""
b1101 [!
b1101 j"
b1101 E"
#180000
0!
0(
#185000
1!
1(
b1110 E"
b1110 j"
b1110 [!
b1110 ""
b1110 q
b1110 8!
#190000
0!
0(
#195000
1!
1(
b1111 8!
b1111 q
b1111 ""
b1111 [!
b1111 j"
b1111 E"
#200000
0!
0(
#205000
1!
1(
0F"
b0 E"
b10000 j"
b110011 Z!
b0 [!
b10000 ""
b1 p
b0 q
b10000 8!
15!
1}!
#210000
0!
0(
#215000
1!
1(
b10001 8!
b1 q
b10001 ""
b1 [!
b10001 j"
b1 E"
#220000
0!
0(
#225000
1!
1(
b10 E"
b10010 j"
b10 [!
b10010 ""
b10 q
b10010 8!
#230000
0!
0(
#235000
1!
1(
b10011 8!
b11 q
b10011 ""
b11 [!
b10011 j"
b11 E"
#240000
0!
0(
#245000
1!
1(
b100 E"
b10100 j"
b100 [!
b10100 ""
b100 q
b10100 8!
#250000
0!
0(
#255000
1!
1(
b10101 8!
b101 q
b10101 ""
b101 [!
b10101 j"
b101 E"
#260000
0!
0(
#265000
1!
1(
b110 E"
b10110 j"
b110 [!
b10110 ""
b110 q
b10110 8!
#270000
0!
0(
#275000
1!
1(
b10111 8!
b111 q
b10111 ""
b111 [!
b10111 j"
b111 E"
#280000
0!
0(
#285000
1!
1(
b1000 E"
b11000 j"
b1000 [!
b11000 ""
b1000 q
b11000 8!
#290000
0!
0(
#295000
1!
1(
b11001 8!
b1001 q
b11001 ""
b1001 [!
b11001 j"
b1001 E"
#300000
0!
0(
#305000
1!
1(
b1010 E"
b11010 j"
b1010 [!
b11010 ""
b1010 q
b11010 8!
#310000
0!
0(
#315000
1!
1(
b11011 8!
b1011 q
b11011 ""
b1011 [!
b11011 j"
b1011 E"
#320000
0!
0(
#325000
1!
1(
b1100 E"
b11100 j"
b1100 [!
b11100 ""
b1100 q
b11100 8!
#330000
0!
0(
#335000
1!
1(
b11101 8!
b1101 q
b11101 ""
b1101 [!
b11101 j"
b1101 E"
#340000
0!
0(
#345000
1!
1(
b1110 E"
b11110 j"
b1110 [!
b11110 ""
b1110 q
b11110 8!
#350000
0!
0(
#355000
1!
1(
b11111 8!
b1111 q
b11111 ""
b1111 [!
b11111 j"
b1111 E"
#360000
0!
0(
#365000
1!
1(
b1100011 D"
b0 E"
b100000 j"
b110100 Z!
b0 [!
b100000 ""
b10 p
b0 q
b100000 8!
05!
14!
0}!
0|!
1{!
1g"
1f"
0e"
#370000
0!
0(
#375000
1!
1(
b100001 8!
b1 q
b100001 ""
b1 [!
b100001 j"
b1 E"
#380000
0!
0(
#385000
1!
1(
b10 E"
b100010 j"
b10 [!
b100010 ""
b10 q
b100010 8!
#390000
0!
0(
#395000
1!
1(
b100011 8!
b11 q
b100011 ""
b11 [!
b100011 j"
b11 E"
#400000
0!
0(
#405000
1!
1(
b100 E"
b100100 j"
b100 [!
b100100 ""
b100 q
b100100 8!
#410000
0!
0(
#415000
1!
1(
b100101 8!
b101 q
b100101 ""
b101 [!
b100101 j"
b101 E"
#420000
0!
0(
#425000
1!
1(
b110 E"
b100110 j"
b110 [!
b100110 ""
b110 q
b100110 8!
#430000
0!
0(
#435000
1!
1(
b100111 8!
b111 q
b100111 ""
b111 [!
b100111 j"
b111 E"
#440000
0!
0(
#445000
1!
1(
b1000 E"
b101000 j"
b1000 [!
b101000 ""
b1000 q
b101000 8!
#450000
0!
0(
#455000
1!
1(
b101001 8!
b1001 q
b101001 ""
b1001 [!
b101001 j"
b1001 E"
#460000
0!
0(
#465000
1!
1(
b1010 E"
b101010 j"
b1010 [!
b101010 ""
b1010 q
b101010 8!
#470000
0!
0(
#475000
1!
1(
b101011 8!
b1011 q
b101011 ""
b1011 [!
b101011 j"
b1011 E"
#480000
0!
0(
#485000
1!
1(
b1100 E"
b101100 j"
b1100 [!
b101100 ""
b1100 q
b101100 8!
#490000
0!
0(
#495000
1!
1(
b101101 8!
b1101 q
b101101 ""
b1101 [!
b101101 j"
b1101 E"
#500000
0!
0(
#505000
1!
1(
b1110 E"
b101110 j"
b1110 [!
b101110 ""
b1110 q
b101110 8!
#510000
0!
0(
#515000
1!
1(
b101111 8!
b1111 q
b101111 ""
b1111 [!
b101111 j"
b1111 E"
#520000
0!
0(
#525000
1!
1(
b1100010 D"
b0 E"
b110000 j"
b110101 Z!
b0 [!
b110000 ""
b11 p
b0 q
b110000 8!
15!
1}!
0g"
#530000
0!
0(
#535000
1!
1(
b110001 8!
b1 q
b110001 ""
b1 [!
b110001 j"
b1 E"
#540000
0!
0(
#545000
1!
1(
b10 E"
b110010 j"
b10 [!
b110010 ""
b10 q
b110010 8!
#550000
0!
0(
#555000
1!
1(
b110011 8!
b11 q
b110011 ""
b11 [!
b110011 j"
b11 E"
#560000
0!
0(
#565000
1!
1(
b100 E"
b110100 j"
b100 [!
b110100 ""
b100 q
b110100 8!
#570000
0!
0(
#575000
1!
1(
b110101 8!
b101 q
b110101 ""
b101 [!
b110101 j"
b101 E"
#580000
0!
0(
#585000
1!
1(
b110 E"
b110110 j"
b110 [!
b110110 ""
b110 q
b110110 8!
#590000
0!
0(
#595000
1!
1(
b110111 8!
b111 q
b110111 ""
b111 [!
b110111 j"
b111 E"
#600000
0!
0(
#605000
1!
1(
b1000 E"
b111000 j"
b1000 [!
b111000 ""
b1000 q
b111000 8!
#610000
0!
0(
#615000
1!
1(
b111001 8!
b1001 q
b111001 ""
b1001 [!
b111001 j"
b1001 E"
#620000
0!
0(
#625000
1!
1(
b1010 E"
b111010 j"
b1010 [!
b111010 ""
b1010 q
b111010 8!
#630000
0!
0(
#635000
1!
1(
b111011 8!
b1011 q
b111011 ""
b1011 [!
b111011 j"
b1011 E"
#640000
0!
0(
#645000
1!
1(
b1100 E"
b111100 j"
b1100 [!
b111100 ""
b1100 q
b111100 8!
#650000
0!
0(
#655000
1!
1(
b111101 8!
b1101 q
b111101 ""
b1101 [!
b111101 j"
b1101 E"
#660000
0!
0(
#665000
1!
1(
b1110 E"
b111110 j"
b1110 [!
b111110 ""
b1110 q
b111110 8!
#670000
0!
0(
#675000
1!
1(
b111111 8!
b1111 q
b111111 ""
b1111 [!
b111111 j"
b1111 E"
#680000
0!
0(
#685000
1!
1(
b1100001 D"
b0 E"
b1000000 j"
b110110 Z!
b0 [!
b1000000 ""
b100 p
b0 q
b1000000 8!
05!
04!
13!
0}!
1|!
1g"
0f"
#690000
0!
0(
#695000
1!
1(
b1000001 8!
b1 q
b1000001 ""
b1 [!
b1000001 j"
b1 E"
#700000
0!
0(
#705000
1!
1(
b10 E"
b1000010 j"
b10 [!
b1000010 ""
b10 q
b1000010 8!
#710000
0!
0(
#715000
1!
1(
b1000011 8!
b11 q
b1000011 ""
b11 [!
b1000011 j"
b11 E"
#720000
0!
0(
#725000
1!
1(
b100 E"
b1000100 j"
b100 [!
b1000100 ""
b100 q
b1000100 8!
#730000
0!
0(
#735000
1!
1(
b1000101 8!
b101 q
b1000101 ""
b101 [!
b1000101 j"
b101 E"
#740000
0!
0(
#745000
1!
1(
b110 E"
b1000110 j"
b110 [!
b1000110 ""
b110 q
b1000110 8!
#750000
0!
0(
#755000
1!
1(
b1000111 8!
b111 q
b1000111 ""
b111 [!
b1000111 j"
b111 E"
#760000
0!
0(
#765000
1!
1(
b1000 E"
b1001000 j"
b1000 [!
b1001000 ""
b1000 q
b1001000 8!
#770000
0!
0(
#775000
1!
1(
b1001001 8!
b1001 q
b1001001 ""
b1001 [!
b1001001 j"
b1001 E"
#780000
0!
0(
#785000
1!
1(
b1010 E"
b1001010 j"
b1010 [!
b1001010 ""
b1010 q
b1001010 8!
#790000
0!
0(
#795000
1!
1(
b1001011 8!
b1011 q
b1001011 ""
b1011 [!
b1001011 j"
b1011 E"
#800000
0!
0(
#805000
1!
1(
b1100 E"
b1001100 j"
b1100 [!
b1001100 ""
b1100 q
b1001100 8!
#810000
0!
0(
#815000
1!
1(
b1001101 8!
b1101 q
b1001101 ""
b1101 [!
b1001101 j"
b1101 E"
#820000
0!
0(
