PWM_LED_Chaser/PWM_LED_Chaser.srcs/sources_1/imports/PWM_LED_Chaser/pwm_generator.v
module pwm_generator #(
	//parameter DUTYCYCLE = 70, //MUST BE an Integer between 0 and the period
	parameter PERIOD = 1000 //MUST BE AN INTEGER GREATER THAN 1. Is number of base clk cycles in a period
)(
	input clk,
	input rst_n,
	input [31:0] duty,
	output reg out,
	output reg error
);
	// Runs once at time 0 in simulation, before any clock edge.
	// PERIOD is a parameter, so this condition is fully determined
	// at elaboration — the check costs zero hardware.
	initial begin
		if (PERIOD < 2) begin
			// %m expands to the full hierarchical instance path, so you
			// find out *which* instantiation was misparameterised.
			// %0d prints the integer with no padding.
			$display("%m: PERIOD must be >= 2, got %0d", PERIOD);
			$finish;
		end
	end

	reg [31:0] counter;
	reg [31:0] duty_D;

	always @(posedge clk) begin
		if (!rst_n) begin
			out <= 1'b0;
			error <= 1'b0;
			counter <= 32'b0;
			duty_D <= 0;
		end else begin
			if (duty_D>PERIOD) begin
				error <= 1'b1;
			end else begin
				error <= 1'b0;
			end

			if (counter == PERIOD - 1) begin
				duty_D <= duty;
				counter <= 32'b0;
			end else begin
				counter <= counter + 1'b1;
			end
			if (counter>=duty_D) begin	
					out <= 1'b0;
			end else begin
				out <= 1'b1;
			end
		end
	end
endmodule

fader.v
//32'd100 is still hardcoded while pwm_generator #() takes PERIOD as a parameter. 
//They agree only because you left the default at 100. Change PERIOD and the fader 
//silently ramps to the wrong ceiling. Make it one shared parameter passed to both —
// this is the constraint about parameterizing timing constants.

//counter == period should be >=. period is an input port, not a parameter. If it 
// drops while counter is already past the new value, you miss the match and stall 
//for 2³² cycles.

//init is unvalidated. The comment says 0–100, nothing enforces it. Feed it 150 and
// the up-ramp never hits == 100, so duty climbs to 4 billion and wraps. The PWM's 
//error will fire, so you'd notice — but the fader itself has no opinion, and error is
// still a bare passthrough.

//Minor: both endpoints are held for two step-periods, since the turnaround cycle flips up without moving duty. Fine if deliberate, worth a comment either way.
//R2 risk: 100 linear steps. The 0→1 step is a doubling of brightness, the 99→100 step is a 1% change. That's the stair-stepping the requirement calls out.
//Fix 1 and 2 before you put it on hardware.







module fader (
    input clk,
    input rst_n,
    input [31:0] period,
    input [31:0] init, // number between 32'd0 and 32'd100
    output out,
    output error
);

    reg [31:0] duty;
    reg [31:0] counter;
    reg up;

    pwm_generator #() PWM(
        .clk(clk),
	    .rst_n(rst_n),
	    .duty(duty),
	    .out(out),
	    .error(error)
    );

    always @(posedge clk) begin
        if (!rst_n) begin
            duty <= init;
            counter <= 32'b0;
            up <= 1'b1;
        end else begin 
            if (counter == period) begin
                if (up) begin
                    if (duty == 32'd100) begin
                        up <= 1'b0;
                    end else begin 
                        duty <= duty + 32'd1;
                    end
                end else begin
                    if (duty == 32'd0) begin
                        up <= 1'b1;
                    end else begin 
                        duty <= duty - 32'd1;
                    end
                end
                counter <= 32'b0;
            end else begin
                counter <= counter + 1'b1;
            end
        end
    end
endmodule

fader_tb.v
`timescale 1ms/1us

module fader_tb;

    reg clk;
    reg rst_n;
    reg [31:0] period1;
    reg [31:0] period2;
    reg [31:0] init1;
    reg [31:0] init2;
    wire out1;
    wire error1;
    wire out2;
    wire error2;

    fader dut_1 (
        .clk(clk),
        .rst_n(rst_n),
        .period(period1),
        .init(init1),
        .out(out1),
        .error(error1)
    );

    fader dut_2 (
        .clk(clk),
        .rst_n(rst_n),
        .period(period2),
        .init(init2),
        .out(out2),
        .error(error2)
    );

    initial clk = 1'b0;
    always #5 clk = ~clk;
    initial init1 = 32'd0;
    initial init2 = 32'd100;

    initial begin
        // Dump waveforms for GTKWave / your viewer of choice
        $dumpfile("fader_tb.vcd");
        $dumpvars(0, fader_tb);

        rst_n = 1'b0;
        period1 = 32'h00000000;
        period2 = 32'h00000000;
        #50
        rst_n = 1'b1;
        period2 = 32'h000000F;
        period1 = 32'h0000000F;
        #50000
        $finish;
    end
endmodule

fader_tb.vcd
$date
	Wed Aug  5 22:16:47 2026
$end
$version
	Questa Altera Starter FPGA Edition Version 2025.2
$end
$timescale
	1us
$end

$scope module fader_tb $end
$var reg 1 ! clk $end
$var reg 1 " rst_n $end
$var reg 32 # period1 [31:0] $end
$var reg 32 $ period2 [31:0] $end
$var reg 32 % init1 [31:0] $end
$var reg 32 & init2 [31:0] $end
$var wire 1 ' out1 $end
$var wire 1 ( error1 $end
$var wire 1 ) out2 $end
$var wire 1 * error2 $end

$scope module dut_1 $end
$var wire 1 + clk $end
$var wire 1 , rst_n $end
$var wire 1 - period [31] $end
$var wire 1 . period [30] $end
$var wire 1 / period [29] $end
$var wire 1 0 period [28] $end
$var wire 1 1 period [27] $end
$var wire 1 2 period [26] $end
$var wire 1 3 period [25] $end
$var wire 1 4 period [24] $end
$var wire 1 5 period [23] $end
$var wire 1 6 period [22] $end
$var wire 1 7 period [21] $end
$var wire 1 8 period [20] $end
$var wire 1 9 period [19] $end
$var wire 1 : period [18] $end
$var wire 1 ; period [17] $end
$var wire 1 < period [16] $end
$var wire 1 = period [15] $end
$var wire 1 > period [14] $end
$var wire 1 ? period [13] $end
$var wire 1 @ period [12] $end
$var wire 1 A period [11] $end
$var wire 1 B period [10] $end
$var wire 1 C period [9] $end
$var wire 1 D period [8] $end
$var wire 1 E period [7] $end
$var wire 1 F period [6] $end
$var wire 1 G period [5] $end
$var wire 1 H period [4] $end
$var wire 1 I period [3] $end
$var wire 1 J period [2] $end
$var wire 1 K period [1] $end
$var wire 1 L period [0] $end
$var wire 1 M init [31] $end
$var wire 1 N init [30] $end
$var wire 1 O init [29] $end
$var wire 1 P init [28] $end
$var wire 1 Q init [27] $end
$var wire 1 R init [26] $end
$var wire 1 S init [25] $end
$var wire 1 T init [24] $end
$var wire 1 U init [23] $end
$var wire 1 V init [22] $end
$var wire 1 W init [21] $end
$var wire 1 X init [20] $end
$var wire 1 Y init [19] $end
$var wire 1 Z init [18] $end
$var wire 1 [ init [17] $end
$var wire 1 \ init [16] $end
$var wire 1 ] init [15] $end
$var wire 1 ^ init [14] $end
$var wire 1 _ init [13] $end
$var wire 1 ` init [12] $end
$var wire 1 a init [11] $end
$var wire 1 b init [10] $end
$var wire 1 c init [9] $end
$var wire 1 d init [8] $end
$var wire 1 e init [7] $end
$var wire 1 f init [6] $end
$var wire 1 g init [5] $end
$var wire 1 h init [4] $end
$var wire 1 i init [3] $end
$var wire 1 j init [2] $end
$var wire 1 k init [1] $end
$var wire 1 l init [0] $end
$var wire 1 ' out $end
$var wire 1 ( error $end
$var reg 32 m duty [31:0] $end
$var reg 32 n counter [31:0] $end
$var reg 1 o up $end

$scope module PWM $end
$var parameter 32 p PERIOD $end
$var wire 1 + clk $end
$var wire 1 , rst_n $end
$var wire 1 q duty [31] $end
$var wire 1 r duty [30] $end
$var wire 1 s duty [29] $end
$var wire 1 t duty [28] $end
$var wire 1 u duty [27] $end
$var wire 1 v duty [26] $end
$var wire 1 w duty [25] $end
$var wire 1 x duty [24] $end
$var wire 1 y duty [23] $end
$var wire 1 z duty [22] $end
$var wire 1 { duty [21] $end
$var wire 1 | duty [20] $end
$var wire 1 } duty [19] $end
$var wire 1 ~ duty [18] $end
$var wire 1 !! duty [17] $end
$var wire 1 "! duty [16] $end
$var wire 1 #! duty [15] $end
$var wire 1 $! duty [14] $end
$var wire 1 %! duty [13] $end
$var wire 1 &! duty [12] $end
$var wire 1 '! duty [11] $end
$var wire 1 (! duty [10] $end
$var wire 1 )! duty [9] $end
$var wire 1 *! duty [8] $end
$var wire 1 +! duty [7] $end
$var wire 1 ,! duty [6] $end
$var wire 1 -! duty [5] $end
$var wire 1 .! duty [4] $end
$var wire 1 /! duty [3] $end
$var wire 1 0! duty [2] $end
$var wire 1 1! duty [1] $end
$var wire 1 2! duty [0] $end
$var reg 1 3! out $end
$var reg 1 4! error $end
$var reg 32 5! counter [31:0] $end
$var reg 32 6! duty_D [31:0] $end
$upscope $end
$upscope $end

$scope module dut_2 $end
$var wire 1 7! clk $end
$var wire 1 8! rst_n $end
$var wire 1 9! period [31] $end
$var wire 1 :! period [30] $end
$var wire 1 ;! period [29] $end
$var wire 1 <! period [28] $end
$var wire 1 =! period [27] $end
$var wire 1 >! period [26] $end
$var wire 1 ?! period [25] $end
$var wire 1 @! period [24] $end
$var wire 1 A! period [23] $end
$var wire 1 B! period [22] $end
$var wire 1 C! period [21] $end
$var wire 1 D! period [20] $end
$var wire 1 E! period [19] $end
$var wire 1 F! period [18] $end
$var wire 1 G! period [17] $end
$var wire 1 H! period [16] $end
$var wire 1 I! period [15] $end
$var wire 1 J! period [14] $end
$var wire 1 K! period [13] $end
$var wire 1 L! period [12] $end
$var wire 1 M! period [11] $end
$var wire 1 N! period [10] $end
$var wire 1 O! period [9] $end
$var wire 1 P! period [8] $end
$var wire 1 Q! period [7] $end
$var wire 1 R! period [6] $end
$var wire 1 S! period [5] $end
$var wire 1 T! period [4] $end
$var wire 1 U! period [3] $end
$var wire 1 V! period [2] $end
$var wire 1 W! period [1] $end
$var wire 1 X! period [0] $end
$var wire 1 Y! init [31] $end
$var wire 1 Z! init [30] $end
$var wire 1 [! init [29] $end
$var wire 1 \! init [28] $end
$var wire 1 ]! init [27] $end
$var wire 1 ^! init [26] $end
$var wire 1 _! init [25] $end
$var wire 1 `! init [24] $end
$var wire 1 a! init [23] $end
$var wire 1 b! init [22] $end
$var wire 1 c! init [21] $end
$var wire 1 d! init [20] $end
$var wire 1 e! init [19] $end
$var wire 1 f! init [18] $end
$var wire 1 g! init [17] $end
$var wire 1 h! init [16] $end
$var wire 1 i! init [15] $end
$var wire 1 j! init [14] $end
$var wire 1 k! init [13] $end
$var wire 1 l! init [12] $end
$var wire 1 m! init [11] $end
$var wire 1 n! init [10] $end
$var wire 1 o! init [9] $end
$var wire 1 p! init [8] $end
$var wire 1 q! init [7] $end
$var wire 1 r! init [6] $end
$var wire 1 s! init [5] $end
$var wire 1 t! init [4] $end
$var wire 1 u! init [3] $end
$var wire 1 v! init [2] $end
$var wire 1 w! init [1] $end
$var wire 1 x! init [0] $end
$var wire 1 ) out $end
$var wire 1 * error $end
$var reg 32 y! duty [31:0] $end
$var reg 32 z! counter [31:0] $end
$var reg 1 {! up $end

$scope module PWM $end
$var parameter 32 |! PERIOD $end
$var wire 1 7! clk $end
$var wire 1 8! rst_n $end
$var wire 1 }! duty [31] $end
$var wire 1 ~! duty [30] $end
$var wire 1 !" duty [29] $end
$var wire 1 "" duty [28] $end
$var wire 1 #" duty [27] $end
$var wire 1 $" duty [26] $end
$var wire 1 %" duty [25] $end
$var wire 1 &" duty [24] $end
$var wire 1 '" duty [23] $end
$var wire 1 (" duty [22] $end
$var wire 1 )" duty [21] $end
$var wire 1 *" duty [20] $end
$var wire 1 +" duty [19] $end
$var wire 1 ," duty [18] $end
$var wire 1 -" duty [17] $end
$var wire 1 ." duty [16] $end
$var wire 1 /" duty [15] $end
$var wire 1 0" duty [14] $end
$var wire 1 1" duty [13] $end
$var wire 1 2" duty [12] $end
$var wire 1 3" duty [11] $end
$var wire 1 4" duty [10] $end
$var wire 1 5" duty [9] $end
$var wire 1 6" duty [8] $end
$var wire 1 7" duty [7] $end
$var wire 1 8" duty [6] $end
$var wire 1 9" duty [5] $end
$var wire 1 :" duty [4] $end
$var wire 1 ;" duty [3] $end
$var wire 1 <" duty [2] $end
$var wire 1 =" duty [1] $end
$var wire 1 >" duty [0] $end
$var reg 1 ?" out $end
$var reg 1 @" error $end
$var reg 32 A" counter [31:0] $end
$var reg 32 B" duty_D [31:0] $end
$upscope $end
$upscope $end
$upscope $end
$enddefinitions $end
#0
$dumpvars
0!
0"
b0 #
b0 $
b0 %
b1100100 &
bx m
bx n
xo
x3!
x4!
bx 5!
bx 6!
bx y!
bx z!
x{!
x?"
x@"
bx A"
bx B"
b1100100 p
b1100100 |!
x'
x(
x)
x*
0x!
0w!
1v!
0u!
0t!
1s!
1r!
0q!
0p!
0o!
0n!
0m!
0l!
0k!
0j!
0i!
0h!
0g!
0f!
0e!
0d!
0c!
0b!
0a!
0`!
0_!
0^!
0]!
0\!
0[!
0Z!
0Y!
0X!
0W!
0V!
0U!
0T!
0S!
0R!
0Q!
0P!
0O!
0N!
0M!
0L!
0K!
0J!
0I!
0H!
0G!
0F!
0E!
0D!
0C!
0B!
0A!
0@!
0?!
0>!
0=!
0<!
0;!
0:!
09!
08!
07!
0l
0k
0j
0i
0h
0g
0f
0e
0d
0c
0b
0a
0`
0_
0^
0]
0\
0[
0Z
0Y
0X
0W
0V
0U
0T
0S
0R
0Q
0P
0O
0N
0M
0L
0K
0J
0I
0H
0G
0F
0E
0D
0C
0B
0A
0@
0?
0>
0=
0<
0;
0:
09
08
07
06
05
04
03
02
01
00
0/
0.
0-
0,
0+
x2!
x1!
x0!
x/!
x.!
x-!
x,!
x+!
x*!
x)!
x(!
x'!
x&!
x%!
x$!
x#!
x"!
x!!
x~
x}
x|
x{
xz
xy
xx
xw
xv
xu
xt
xs
xr
xq
x>"
x="
x<"
x;"
x:"
x9"
x8"
x7"
x6"
x5"
x4"
x3"
x2"
x1"
x0"
x/"
x."
x-"
x,"
x+"
x*"
x)"
x("
x'"
x&"
x%"
x$"
x#"
x""
x!"
x~!
x}!
$end
#5000
1!
1+
17!
0?"
0@"
b0 A"
b0 B"
b1100100 y!
b0 z!
1{!
03!
04!
b0 5!
b0 6!
b0 m
b0 n
1o
0)
0*
0'
0(
02!
01!
00!
0/!
0.!
0-!
0,!
0+!
0*!
0)!
0(!
0'!
0&!
0%!
0$!
0#!
0"!
0!!
0~
0}
0|
0{
0z
0y
0x
0w
0v
0u
0t
0s
0r
0q
0>"
0="
1<"
0;"
0:"
19"
18"
07"
06"
05"
04"
03"
02"
01"
00"
0/"
0."
0-"
0,"
0+"
0*"
0)"
0("
0'"
0&"
0%"
0$"
0#"
0""
0!"
0~!
0}!
#10000
0!
0+
07!
#15000
1!
1+
17!
#20000
0!
0+
07!
#25000
1!
1+
17!
#30000
0!
0+
07!
#35000
1!
1+
17!
#40000
0!
0+
07!
#45000
1!
1+
17!
#50000
1"
b1111 $
b1111 #
0!
1,
18!
1L
1K
1J
1I
1X!
1W!
1V!
1U!
0+
07!
#55000
1!
1+
17!
b1 A"
b1 z!
b1 5!
b1 n
#60000
0!
0+
07!
#65000
1!
1+
17!
b10 z!
b10 A"
b10 n
b10 5!
#70000
0!
0+
07!
#75000
1!
1+
17!
b11 A"
b11 z!
b11 5!
b11 n
#80000
0!
0+
07!
#85000
1!
1+
17!
b100 z!
b100 A"
b100 n
b100 5!
#90000
0!
0+
07!
#95000
1!
1+
17!
b101 A"
b101 z!
b101 5!
b101 n
#100000
0!
0+
07!
#105000
1!
1+
17!
b110 z!
b110 A"
b110 n
b110 5!
#110000
0!
0+
07!
#115000
1!
1+
17!
b111 A"
b111 z!
b111 5!
b111 n
#120000
0!
0+
07!
#125000
1!
1+
17!
b1000 z!
b1000 A"
b1000 n
b1000 5!
#130000
0!
0+
07!
#135000
1!
1+
17!
b1001 A"
b1001 z!
b1001 5!
b1001 n
#140000
0!
0+
07!
#145000
1!
1+
17!
b1010 z!
b1010 A"
b1010 n
b1010 5!
#150000
0!
0+
07!
#155000
1!
1+
17!
b1011 A"
b1011 z!
b1011 5!
b1011 n
#160000
0!
0+
07!
#165000
1!
1+
17!
b1100 z!
b1100 A"
b1100 n
b1100 5!
#170000
0!
0+
07!
#175000
1!
1+
17!
b1101 A"
b1101 z!
b1101 5!
b1101 n
#180000
0!
0+
07!
#185000
1!
1+
17!
b1110 z!
b1110 A"
b1110 n
b1110 5!
#190000
0!
0+
07!
#195000
1!
1+
17!
b1111 A"
b1111 z!
b1111 5!
b1111 n
#200000
0!
0+
07!
#205000
1!
1+
17!
0{!
b0 z!
b10000 A"
b1 m
b0 n
b10000 5!
12!
#210000
0!
0+
07!
#215000
1!
1+
17!
b10001 A"
b1 z!
b10001 5!
b1 n
#220000
0!
0+
07!
#225000
1!
1+
17!
b10 z!
b10010 A"
b10 n
b10010 5!
#230000
0!
0+
07!
#235000
1!
1+
17!
b10011 A"
b11 z!
b10011 5!
b11 n
#240000
0!
0+
07!
#245000
1!
1+
17!
b100 z!
b10100 A"
b100 n
b10100 5!
#250000
0!
0+
07!
#255000
1!
1+
17!
b10101 A"
b101 z!
b10101 5!
b101 n
#260000
0!
0+
07!
#265000
1!
1+
17!
b110 z!
b10110 A"
b110 n
b10110 5!
#270000
0!
0+
07!
#275000
1!
1+
17!
b10111 A"
b111 z!
b10111 5!
b111 n
#280000
0!
0+
07!
#285000
1!
1+
17!
b1000 z!
b11000 A"
b1000 n
b11000 5!
#290000
0!
0+
07!
#295000
1!
1+
17!
b11001 A"
b1001 z!
b11001 5!
b1001 n
#300000
0!
0+
07!
#305000
1!
1+
17!
b1010 z!
b11010 A"
b1010 n
b11010 5!
#310000
0!
0+
07!
#315000
1!
1+
17!
b11011 A"
b1011 z!
b11011 5!
b1011 n
#320000
0!
0+
07!
#325000
1!
1+
17!
b1100 z!
b11100 A"
b1100 n
b11100 5!
#330000
0!
0+
07!
#335000
1!
1+
17!
b11101 A"
b1101 z!
b11101 5!
b1101 n
#340000
0!
0+
07!
#345000
1!
1+
17!
b1110 z!
b11110 A"
b1110 n
b11110 5!
#350000
0!
0+
07!
#355000
1!
1+
17!
b11111 A"
b1111 z!
b11111 5!
b1111 n
#360000
0!
0+
07!
#365000
1!
1+
17!
b1100011 y!
b0 z!
b100000 A"
b10 m
b0 n
b100000 5!
02!
11!
1>"
1="
0<"
#370000
0!
0+
07!
#375000
1!
1+
17!
b100001 A"
b1 z!
b100001 5!
b1 n
#380000
0!
0+
07!
#385000
1!
1+
17!
b10 z!
b100010 A"
b10 n
b100010 5!
#390000
0!
0+
07!
#395000
1!
1+
17!
b100011 A"
b11 z!
b100011 5!
b11 n
#400000
0!
0+
07!
#405000
1!
1+
17!
b100 z!
b100100 A"
b100 n
b100100 5!
#410000
0!
0+
07!
#415000
1!
1+
17!
b100101 A"
b101 z!
b100101 5!
b101 n
#420000
0!
0+
07!
#425000
1!
1+
17!
b110 z!
b100110 A"
b110 n
b100110 5!
#430000
0!
0+
07!
#435000
1!
1+
17!
b100111 A"
b111 z!
b100111 5!
b111 n
#440000
0!
0+
07!
#445000
1!
1+
17!
b1000 z!
b101000 A"
b1000 n
b101000 5!
#450000
0!
0+
07!
#455000
1!
1+
17!
b101001 A"
b1001 z!
b101001 5!
b1001 n
#460000
0!
0+
07!
#465000
1!
1+
17!
b1010 z!
b101010 A"
b1010 n
b101010 5!
#470000
0!
0+
07!
#475000
1!
1+
17!
b101011 A"
b1011 z!
b101011 5!
b1011 n
#480000
0!
0+
07!
#485000
1!
1+
17!
b1100 z!
b101100 A"
b1100 n
b101100 5!
#490000
0!
0+
07!
#495000
1!
1+
17!
b101101 A"
b1101 z!
b101101 5!
b1101 n
#500000
0!
0+
07!
#505000
1!
1+
17!
b1110 z!
b101110 A"
b1110 n
b101110 5!
#510000
0!
0+
07!
#515000
1!
1+
17!
b101111 A"
b1111 z!
b101111 5!
b1111 n
#520000
0!
0+
07!
#525000
1!
1+
17!
b1100010 y!
b0 z!
b110000 A"
b11 m
b0 n
b110000 5!
12!
0>"
#530000
0!
0+
07!
#535000
1!
1+
17!
b110001 A"
b1 z!
b110001 5!
b1 n
#540000
0!
0+
07!
#545000
1!
1+
17!
b10 z!
b110010 A"
b10 n
b110010 5!
#550000
0!
0+
07!
#555000
1!
1+
17!
b110011 A"
b11 z!
b110011 5!
b11 n
#560000
0!
0+
07!
#565000
1!
1+
17!
b100 z!
b110100 A"
b100 n
b110100 5!
#570000
0!
0+
07!
#575000
1!
1+
17!
b110101 A"
b101 z!
b110101 5!
b101 n
#580000
0!
0+
07!
#585000
1!
1+
17!
b110 z!
b110110 A"
b110 n
b110110 5!
#590000
0!
0+
07!
#595000
1!
1+
17!
b110111 A"
b111 z!
b110111 5!
b111 n
#600000
0!
0+
07!
#605000
1!
1+
17!
b1000 z!
b111000 A"
b1000 n
b111000 5!
#610000
0!
0+
07!
#615000
1!
1+
17!
b111001 A"
b1001 z!
b111001 5!
b1001 n
#620000
0!
0+
07!
#625000
1!
1+
17!
b1010 z!
b111010 A"
b1010 n
b111010 5!
#630000
0!
0+
07!
#635000
1!
1+
17!
b111011 A"
b1011 z!
b111011 5!
b1011 n
#640000
0!
0+
07!
#645000
1!
1+
17!
b1100 z!
b111100 A"
b1100 n
b111100 5!
#650000
0!
0+
07!
#655000
1!
1+
17!
b111101 A"
b1101 z!
b111101 5!
b1101 n
#660000
0!
0+
07!
#665000
1!
1+
17!
b1110 z!
b111110 A"
b1110 n
b111110 5!
#670000
0!
0+
07!
#675000
1!
1+
17!
b111111 A"
b1111 z!
b111111 5!
b1111 n
#680000
0!
0+
07!
#685000
1!
1+
17!
b1100001 y!
b0 z!
b1000000 A"
b100 m
b0 n
b1000000 5!
02!
01!
10!
1>"
0="
#690000
0!
0+
07!
#695000
1!
1+
17!
b1000001 A"
b1 z!
b1000001 5!
b1 n
#700000
0!
0+
07!
#705000
1!
1+
17!
b10 z!
b1000010 A"
b10 n
b1000010 5!
#710000
0!
0+
07!
#715000
1!
1+
17!
b1000011 A"
b11 z!
b1000011 5!
b11 n
#720000
0!
0+
07!
#725000
1!
1+
17!
b100 z!
b1000100 A"
b100 n
b1000100 5!
#730000
0!
0+
07!
#735000
1!
1+
17!
b1000101 A"
b101 z!
b1000101 5!
b101 n
#740000
0!
0+
07!
#745000
1!
1+
17!
b110 z!
b1000110 A"
b110 n
b1000110 5!
#750000
0!
0+
07!
#755000
1!
1+
17!
b1000111 A"
b111 z!
b1000111 5!
b111 n
#760000
0!
0+
07!
#765000
1!
1+
17!
b1000 z!
b1001000 A"
b1000 n
b1001000 5!
#770000
0!
0+
07!
#775000
1!
1+
17!
b1001001 A"
b1001 z!
b1001001 5!
b1001 n
#780000
0!
0+
07!
#785000
1!
1+
17!
b1010 z!
b1001010 A"
b1010 n
b1001010 5!
#790000
0!
0+
07!
#795000
1!
1+
17!
b1001011 A"
b1011 z!
b1001011 5!
b1011 n
#800000
0!
0+
07!
#805000
1!
1+
17!
b1100 z!
b1001100 A"
b1100 n
b1001100 5!
#810000
0!
0+
07!
#815000
1!
1+
17!
b1001101 A"
b1101 z!
b1001101 5!
b1101 n
#820000
0!
0+
07!
#825000
1!
1+
17!
b1110 z!
b1001110 A"
b1110 n
b1001110 5!
#830000
0!
0+
07!
#835000
1!
1+
17!
b1001111 A"
b1111 z!
b1001111 5!
b1111 n
#840000
0!
0+
07!
#845000
1!
1+
17!
b1100000 y!
b0 z!
b1010000 A"
b101 m
b0 n
b1010000 5!
12!
0>"
#850000
0!
0+
07!
#855000
1!
1+
17!
b1010001 A"
b1 z!
b1010001 5!
b1 n
#860000
0!
0+
07!
#865000
1!
1+
17!
b10 z!
b1010010 A"
b10 n
b1010010 5!
#870000
0!
0+
07!
#875000
1!
1+
17!
b1010011 A"
b11 z!
b1010011 5!
b11 n
#880000
0!
0+
07!
#885000
1!
1+
17!
b100 z!
b1010100 A"
b100 n
b1010100 5!
#890000
0!
0+
07!
#895000
1!
1+
17!
b1010101 A"
b101 z!
b1010101 5!
b101 n
#900000
0!
0+
07!
#905000
1!
1+
17!
b110 z!
b1010110 A"
b110 n
b1010110 5!
#910000
0!
0+
07!
#915000
1!
1+
17!
b1010111 A"
b111 z!
b1010111 5!
b111 n
#920000
0!
0+
07!
#925000
1!
1+
17!
b1000 z!
b1011000 A"
b1000 n
b1011000 5!
#930000
0!
0+
07!
#935000
1!
1+
17!
b1011001 A"
b1001 z!
b1011001 5!
b1001 n
#940000
0!
0+
07!
#945000
1!
1+
17!
b1010 z!
b1011010 A"
b1010 n
b1011010 5!
#950000
0!
0+
07!
#955000
1!
1+
17!
b1011011 A"
b1011 z!
b1011011 5!
b1011 n
#960000
0!
0+
07!
#965000
1!
1+
17!
b1100 z!
b1011100 A"
b1100 n
b1011100 5!
#970000
0!
0+
07!
#975000
1!
1+
17!
b1011101 A"
b1101 z!
b1011101 5!
b1101 n
#980000
0!
0+
07!
#985000
1!
1+
17!
b1110 z!
b1011110 A"
b1110 n
b1011110 5!
#990000
0!
0+
07!
#995000
1!
1+
17!
b1011111 A"
b1111 z!
b1011111 5!
b1111 n
#1000000
0!
0+
07!
#1005000
1!
1+
17!
b1011111 y!
b0 z!
b1100000 A"
b110 m
b0 n
b1100000 5!
02!
11!
1>"
1="
1<"
1;"
1:"
09"
#1010000
0!
0+
07!
#1015000
1!
1+
17!
b1100001 A"
b1 z!
b1100001 5!
b1 n
#1020000
0!
0+
07!
#1025000
1!
1+
17!
b10 z!
b1100010 A"
b10 n
b1100010 5!
#1030000
0!
0+
07!
#1035000
1!
1+
17!
b1100011 A"
b11 z!
b1100011 5!
b11 n
#1040000
0!
0+
07!
#1045000
1!
1+
17!
b100 z!
b1011111 B"
b0 A"
b100 n
b110 6!
b0 5!
#1050000
0!
0+
07!
#1055000
1!
1+
17!
b1 A"
1?"
b101 z!
b1 5!
13!
b101 n
1)
1'
#1060000
0!
0+
07!
#1065000
1!
1+
17!
b110 z!
b10 A"
b110 n
b10 5!
#1070000
0!
0+
07!
#1075000
1!
1+
17!
b11 A"
b111 z!
b11 5!
b111 n
#1080000
0!
0+
07!
#1085000
1!
1+
17!
b1000 z!
b100 A"
b1000 n
b100 5!
#1090000
0!
0+
07!
#1095000
1!
1+
17!
b101 A"
b1001 z!
b101 5!
b1001 n
#1100000
0!
0+
07!
#1105000
1!
1+
17!
b1010 z!
b110 A"
b1010 n
b110 5!
#1110000
0!
0+
07!
#1115000
1!
1+
17!
b111 A"
b1011 z!
b111 5!
03!
b1011 n
0'
#1120000
0!
0+
07!
#1125000
1!
1+
17!
b1100 z!
b1000 A"
b1100 n
b1000 5!
#1130000
0!
0+
07!
#1135000
1!
1+
17!
b1001 A"
b1101 z!
b1001 5!
b1101 n
#1140000
0!
0+
07!
#1145000
1!
1+
17!
b1110 z!
b1010 A"
b1110 n
b1010 5!
#1150000
0!
0+
07!
#1155000
1!
1+
17!
b1011 A"
b1111 z!
b1011 5!
b1111 n
#1160000
0!
0+
07!
#1165000
1!
1+
17!
b1011110 y!
b0 z!
b1100 A"
b111 m
b0 n
b1100 5!
12!
0>"
#1170000
0!
0+
07!
#1175000
1!
1+
17!
b1101 A"
b1 z!
b1101 5!
b1 n
#1180000
0!
0+
07!
#1185000
1!
1+
17!
b10 z!
b1110 A"
b10 n
b1110 5!
#1190000
0!
0+
07!
#1195000
1!
1+
17!
b1111 A"
b11 z!
b1111 5!
b11 n
#1200000
0!
0+
07!
#1205000
1!
1+
17!
b100 z!
b10000 A"
b100 n
b10000 5!
#1210000
0!
0+
07!
#1215000
1!
1+
17!
b10001 A"
b101 z!
b10001 5!
b101 n
#1220000
0!
0+
07!
#1225000
1!
1+
17!
b110 z!
b10010 A"
b110 n
b10010 5!
#1230000
0!
0+
07!
#1235000
1!
1+
17!
b10011 A"
b111 z!
b10011 5!
b111 n
#1240000
0!
0+
07!
#1245000
1!
1+
17!
b1000 z!
b10100 A"
b1000 n
b10100 5!
#1250000
0!
0+
07!
#1255000
1!
1+
17!
b10101 A"
b1001 z!
b10101 5!
b1001 n
#1260000
0!
0+
07!
#1265000
1!
1+
17!
b1010 z!
b10110 A"
b1010 n
b10110 5!
#1270000
0!
0+
07!
#1275000
1!
1+
17!
b10111 A"
b1011 z!
b10111 5!
b1011 n
#1280000
0!
0+
07!
#1285000
1!
1+
17!
b1100 z!
b11000 A"
b1100 n
b11000 5!
#1290000
0!
0+
07!
#1295000
1!
1+
17!
b11001 A"
b1101 z!
b11001 5!
b1101 n
#1300000
0!
0+
07!
#1305000
1!
1+
17!
b1110 z!
b11010 A"
b1110 n
b11010 5!
#1310000
0!
0+
07!
#1315000
1!
1+
17!
b11011 A"
b1111 z!
b11011 5!
b1111 n
#1320000
0!
0+
07!
#1325000
1!
1+
17!
b1011101 y!
b0 z!
b11100 A"
b1000 m
b0 n
b11100 5!
02!
01!
00!
1/!
1>"
0="
#1330000
0!
0+
07!
#1335000
1!
1+
17!
b11101 A"
b1 z!
b11101 5!
b1 n
#1340000
0!
0+
07!
#1345000
1!
1+
17!
b10 z!
b11110 A"
b10 n
b11110 5!
#1350000
0!
0+
07!
#1355000
1!
1+
17!
b11111 A"
b11 z!
b11111 5!
b11 n
#1360000
0!
0+
07!
#1365000
1!
1+
17!
b100 z!
b100000 A"
b100 n
b100000 5!
#1370000
0!
0+
07!
#1375000
1!
1+
17!
b100001 A"
b101 z!
b100001 5!
b101 n
#1380000
0!
0+
07!
#1385000
1!
1+
17!
b110 z!
b100010 A"
b110 n
b100010 5!
#1390000
0!
0+
07!
#1395000
1!
1+
17!
b100011 A"
b111 z!
b100011 5!
b111 n
#1400000
0!
0+
07!
#1405000
1!
1+
17!
b1000 z!
b100100 A"
b1000 n
b100100 5!
#1410000
0!
0+
07!
#1415000
1!
1+
17!
b100101 A"
b1001 z!
b100101 5!
b1001 n
#1420000
0!
0+
07!
#1425000
1!
1+
17!
b1010 z!
b100110 A"
b1010 n
b100110 5!
#1430000
0!
0+
07!
#1435000
1!
1+
17!
b100111 A"
b1011 z!
b100111 5!
b1011 n
#1440000
0!
0+
07!
#1445000
1!
1+
17!
b1100 z!
b101000 A"
b1100 n
b101000 5!
#1450000
0!
0+
07!
#1455000
1!
1+
17!
b101001 A"
b1101 z!
b101001 5!
b1101 n
#1460000
0!
0+
07!
#1465000
1!
1+
17!
b1110 z!
b101010 A"
b1110 n
b101010 5!
#1470000
0!
0+
07!
#1475000
1!
1+
17!
b101011 A"
b1111 z!
b101011 5!
b1111 n
#1480000
0!
0+
07!
