PWM_LED_Chaser/PWM_LED_Chaser.srcs/sources_1/imports/PWM_LED_Chaser/pwm_generator.v
module pwm_generator #(
	//parameter DUTYCYCLE = 70, //MUST BE an Integer between 0 and the period
	parameter PERIOD = 1000 //MUST BE AN INTEGER GREATER THAN 1. Is number of base clk cycles in a period
)(
	input clk,
	input rst_n,
	input [31:0] duty,
	output reg out,
	output reg error
);
	// Runs once at time 0 in simulation, before any clock edge.
	// PERIOD is a parameter, so this condition is fully determined
	// at elaboration — the check costs zero hardware.
	initial begin
		if (PERIOD < 2) begin
			// %m expands to the full hierarchical instance path, so you
			// find out *which* instantiation was misparameterised.
			// %0d prints the integer with no padding.
			$display("%m: PERIOD must be >= 2, got %0d", PERIOD);
			$finish;
		end
	end

	reg [31:0] counter;
	reg [31:0] duty_D;

	always @(posedge clk) begin
		if (!rst_n) begin
			out <= 1'b0;
			error <= 1'b0;
			counter <= 32'b0;
			duty_D <= 0;
		end else begin
			if (duty_D>PERIOD) begin
				error <= 1'b1;
			end else begin
				error <= 1'b0;
			end

			if (counter == PERIOD - 1) begin
				duty_D <= duty;
				counter <= 32'b0;
			end else begin
				counter <= counter + 1'b1;
			end
			if (counter>=duty_D) begin	
					out <= 1'b0;
			end else begin
				out <= 1'b1;
			end
		end
	end
endmodule

fader.v
module fader (
    input clk,
    input rst_n,
    input [31:0] period,
    output out,
    output error
);

    reg [31:0] duty = 32'b0;
    reg [31:0] counter = 32'b0;
    reg up = 1'b1;

    pwm_generator #() PWM(
        .clk(clk),
	    .rst_n(rst_n),
	    .duty(duty),
	    .out(out),
	    .error(error)
    );

    always @(posedge clk) begin
        if (!rst_n) begin
            duty <= 32'b0;
            counter <= 32'b0;
        end else begin 
            if (counter == period) begin
                if (up) begin
                    if (duty == 32'd100) begin
                        up <= 1'b0;
                    end else begin 
                        duty = duty + 32'd1;
                    end
                end else begin
                    if (duty == 32'd0) begin
                        up <= 1'b1;
                    end else begin 
                        duty = duty - 32'd1;
                    end
                end
                counter <= 32'b0;
            end else begin
                counter <= counter + 1'b1;
            end
        end
    end
endmodule

fader_tb.v
`timescale 1ms/1us

module fader_tb;

    reg clk;
    reg rst_n;
    reg [31:0] period;
    wire out;
    wire error;

    fader dut (
        .clk(clk),
        .rst_n(rst_n),
        .period(period),
        .out(out),
        .error(error)
    );

    initial clk = 1'b0;
    always #5 clk = ~clk;

    initial begin
        // Dump waveforms for GTKWave / your viewer of choice
        $dumpfile("fader_tb.vcd");
        $dumpvars(0, fader_tb);

        rst_n = 1'b0;
        period = 32'h00000000;
        #50
        rst_n = 1'b1;
        period = 32'h0000000F;
        #50000
        $finish;
    end
endmodule

fader_tb.vcd
$date
	Mon Aug  3 22:41:40 2026
$end
$version
	Questa Altera Starter FPGA Edition Version 2025.2
$end
$timescale
	1us
$end

$scope module fader_tb $end
$var reg 1 ! clk $end
$var reg 1 " rst_n $end
$var reg 32 # period [31:0] $end
$var wire 1 $ out $end
$var wire 1 % error $end

$scope module dut $end
$var wire 1 & clk $end
$var wire 1 ' rst_n $end
$var wire 1 ( period [31] $end
$var wire 1 ) period [30] $end
$var wire 1 * period [29] $end
$var wire 1 + period [28] $end
$var wire 1 , period [27] $end
$var wire 1 - period [26] $end
$var wire 1 . period [25] $end
$var wire 1 / period [24] $end
$var wire 1 0 period [23] $end
$var wire 1 1 period [22] $end
$var wire 1 2 period [21] $end
$var wire 1 3 period [20] $end
$var wire 1 4 period [19] $end
$var wire 1 5 period [18] $end
$var wire 1 6 period [17] $end
$var wire 1 7 period [16] $end
$var wire 1 8 period [15] $end
$var wire 1 9 period [14] $end
$var wire 1 : period [13] $end
$var wire 1 ; period [12] $end
$var wire 1 < period [11] $end
$var wire 1 = period [10] $end
$var wire 1 > period [9] $end
$var wire 1 ? period [8] $end
$var wire 1 @ period [7] $end
$var wire 1 A period [6] $end
$var wire 1 B period [5] $end
$var wire 1 C period [4] $end
$var wire 1 D period [3] $end
$var wire 1 E period [2] $end
$var wire 1 F period [1] $end
$var wire 1 G period [0] $end
$var wire 1 $ out $end
$var wire 1 % error $end
$var reg 32 H duty [31:0] $end
$var reg 32 I counter [31:0] $end
$var reg 1 J up $end

$scope module PWM $end
$var parameter 32 K PERIOD $end
$var wire 1 & clk $end
$var wire 1 ' rst_n $end
$var wire 1 L duty [31] $end
$var wire 1 M duty [30] $end
$var wire 1 N duty [29] $end
$var wire 1 O duty [28] $end
$var wire 1 P duty [27] $end
$var wire 1 Q duty [26] $end
$var wire 1 R duty [25] $end
$var wire 1 S duty [24] $end
$var wire 1 T duty [23] $end
$var wire 1 U duty [22] $end
$var wire 1 V duty [21] $end
$var wire 1 W duty [20] $end
$var wire 1 X duty [19] $end
$var wire 1 Y duty [18] $end
$var wire 1 Z duty [17] $end
$var wire 1 [ duty [16] $end
$var wire 1 \ duty [15] $end
$var wire 1 ] duty [14] $end
$var wire 1 ^ duty [13] $end
$var wire 1 _ duty [12] $end
$var wire 1 ` duty [11] $end
$var wire 1 a duty [10] $end
$var wire 1 b duty [9] $end
$var wire 1 c duty [8] $end
$var wire 1 d duty [7] $end
$var wire 1 e duty [6] $end
$var wire 1 f duty [5] $end
$var wire 1 g duty [4] $end
$var wire 1 h duty [3] $end
$var wire 1 i duty [2] $end
$var wire 1 j duty [1] $end
$var wire 1 k duty [0] $end
$var reg 1 l out $end
$var reg 1 m error $end
$var reg 32 n counter [31:0] $end
$var reg 32 o duty_D [31:0] $end
$upscope $end
$upscope $end
$upscope $end
$enddefinitions $end
#0
$dumpvars
0!
0"
b0 #
b0 H
b0 I
1J
xl
xm
bx n
bx o
b1100100 K
x$
x%
0G
0F
0E
0D
0C
0B
0A
0@
0?
0>
0=
0<
0;
0:
09
08
07
06
05
04
03
02
01
00
0/
0.
0-
0,
0+
0*
0)
0(
0'
0&
0k
0j
0i
0h
0g
0f
0e
0d
0c
0b
0a
0`
0_
0^
0]
0\
0[
0Z
0Y
0X
0W
0V
0U
0T
0S
0R
0Q
0P
0O
0N
0M
0L
$end
#5000
1!
1&
0l
0m
b0 n
b0 o
0$
0%
#10000
0!
0&
#15000
1!
1&
#20000
0!
0&
#25000
1!
1&
#30000
0!
0&
#35000
1!
1&
#40000
0!
0&
#45000
1!
1&
#50000
1"
b1111 #
0!
1'
1G
1F
1E
1D
0&
#55000
1!
1&
b1 n
b1 I
#60000
0!
0&
#65000
1!
1&
b10 I
b10 n
#70000
0!
0&
#75000
1!
1&
b11 n
b11 I
#80000
0!
0&
#85000
1!
1&
b100 I
b100 n
#90000
0!
0&
#95000
1!
1&
b101 n
b101 I
#100000
0!
0&
#105000
1!
1&
b110 I
b110 n
#110000
0!
0&
#115000
1!
1&
b111 n
b111 I
#120000
0!
0&
#125000
1!
1&
b1000 I
b1000 n
#130000
0!
0&
#135000
1!
1&
b1001 n
b1001 I
#140000
0!
0&
#145000
1!
1&
b1010 I
b1010 n
#150000
0!
0&
#155000
1!
1&
b1011 n
b1011 I
#160000
0!
0&
#165000
1!
1&
b1100 I
b1100 n
#170000
0!
0&
#175000
1!
1&
b1101 n
b1101 I
#180000
0!
0&
#185000
1!
1&
b1110 I
b1110 n
#190000
0!
0&
#195000
1!
1&
b1111 n
b1111 I
#200000
0!
0&
#205000
1!
1&
b1 H
1k
b0 I
b10000 n
#210000
0!
0&
#215000
1!
1&
b10001 n
b1 I
#220000
0!
0&
#225000
1!
1&
b10 I
b10010 n
#230000
0!
0&
#235000
1!
1&
b10011 n
b11 I
#240000
0!
0&
#245000
1!
1&
b100 I
b10100 n
#250000
0!
0&
#255000
1!
1&
b10101 n
b101 I
#260000
0!
0&
#265000
1!
1&
b110 I
b10110 n
#270000
0!
0&
#275000
1!
1&
b10111 n
b111 I
#280000
0!
0&
#285000
1!
1&
b1000 I
b11000 n
#290000
0!
0&
#295000
1!
1&
b11001 n
b1001 I
#300000
0!
0&
#305000
1!
1&
b1010 I
b11010 n
#310000
0!
0&
#315000
1!
1&
b11011 n
b1011 I
#320000
0!
0&
#325000
1!
1&
b1100 I
b11100 n
#330000
0!
0&
#335000
1!
1&
b11101 n
b1101 I
#340000
0!
0&
#345000
1!
1&
b1110 I
b11110 n
#350000
0!
0&
#355000
1!
1&
b11111 n
b1111 I
#360000
0!
0&
#365000
1!
1&
b10 H
0k
1j
b0 I
b100000 n
#370000
0!
0&
#375000
1!
1&
b100001 n
b1 I
#380000
0!
0&
#385000
1!
1&
b10 I
b100010 n
#390000
0!
0&
#395000
1!
1&
b100011 n
b11 I
#400000
0!
0&
#405000
1!
1&
b100 I
b100100 n
#410000
0!
0&
#415000
1!
1&
b100101 n
b101 I
#420000
0!
0&
#425000
1!
1&
b110 I
b100110 n
#430000
0!
0&
#435000
1!
1&
b100111 n
b111 I
#440000
0!
0&
#445000
1!
1&
b1000 I
b101000 n
#450000
0!
0&
#455000
1!
1&
b101001 n
b1001 I
#460000
0!
0&
#465000
1!
1&
b1010 I
b101010 n
#470000
0!
0&
#475000
1!
1&
b101011 n
b1011 I
#480000
0!
0&
#485000
1!
1&
b1100 I
b101100 n
#490000
0!
0&
#495000
1!
1&
b101101 n
b1101 I
#500000
0!
0&
#505000
1!
1&
b1110 I
b101110 n
#510000
0!
0&
#515000
1!
1&
b101111 n
b1111 I
#520000
0!
0&
#525000
1!
1&
b11 H
1k
b0 I
b110000 n
#530000
0!
0&
#535000
1!
1&
b110001 n
b1 I
#540000
0!
0&
#545000
1!
1&
b10 I
b110010 n
#550000
0!
0&
#555000
1!
1&
b110011 n
b11 I
#560000
0!
0&
#565000
1!
1&
b100 I
b110100 n
#570000
0!
0&
#575000
1!
1&
b110101 n
b101 I
#580000
0!
0&
#585000
1!
1&
b110 I
b110110 n
#590000
0!
0&
#595000
1!
1&
b110111 n
b111 I
#600000
0!
0&
#605000
1!
1&
b1000 I
b111000 n
#610000
0!
0&
#615000
1!
1&
b111001 n
b1001 I
#620000
0!
0&
#625000
1!
1&
b1010 I
b111010 n
#630000
0!
0&
#635000
1!
1&
b111011 n
b1011 I
#640000
0!
0&
#645000
1!
1&
b1100 I
b111100 n
#650000
0!
0&
#655000
1!
1&
b111101 n
b1101 I
#660000
0!
0&
#665000
1!
1&
b1110 I
b111110 n
#670000
0!
0&
#675000
1!
1&
b111111 n
b1111 I
#680000
0!
0&
#685000
1!
1&
b100 H
0k
0j
1i
b0 I
b1000000 n
#690000
0!
0&
#695000
1!
1&
b1000001 n
b1 I
#700000
0!
0&
#705000
1!
1&
b10 I
b1000010 n
#710000
0!
0&
#715000
1!
1&
b1000011 n
b11 I
#720000
0!
0&
#725000
1!
1&
b100 I
b1000100 n
#730000
0!
0&
#735000
1!
1&
b1000101 n
b101 I
#740000
0!
0&
#745000
1!
1&
b110 I
b1000110 n
#750000
0!
0&
#755000
1!
1&
b1000111 n
b111 I
#760000
0!
0&
#765000
1!
1&
b1000 I
b1001000 n
#770000
0!
0&
#775000
1!
1&
b1001001 n
b1001 I
#780000
0!
0&
#785000
1!
1&
b1010 I
b1001010 n
#790000
0!
0&
#795000
1!
1&
b1001011 n
b1011 I
#800000
0!
0&
#805000
1!
1&
b1100 I
b1001100 n
#810000
0!
0&
#815000
1!
1&
b1001101 n
b1101 I
#820000
0!
0&
#825000
1!
1&
b1110 I
b1001110 n
#830000
0!
0&
#835000
1!
1&
b1001111 n
b1111 I
#840000
0!
0&
#845000
1!
1&
b101 H
1k
b0 I
b1010000 n
#850000
0!
0&
#855000
1!
1&
b1010001 n
b1 I
#860000
0!
0&
#865000
1!
1&
b10 I
b1010010 n
#870000
0!
0&
#875000
1!
1&
b1010011 n
b11 I
#880000
0!
0&
#885000
1!
1&
b100 I
b1010100 n
#890000
0!
0&
#895000
1!
1&
b1010101 n
b101 I
#900000
0!
0&
#905000
1!
1&
b110 I
b1010110 n
#910000
0!
0&
#915000
1!
1&
b1010111 n
b111 I
#920000
0!
0&
#925000
1!
1&
b1000 I
b1011000 n
#930000
0!
0&
#935000
1!
1&
b1011001 n
b1001 I
#940000
0!
0&
#945000
1!
1&
b1010 I
b1011010 n
#950000
0!
0&
#955000
1!
1&
b1011011 n
b1011 I
#960000
0!
0&
#965000
1!
1&
b1100 I
b1011100 n
#970000
0!
0&
#975000
1!
1&
b1011101 n
b1101 I
#980000
0!
0&
#985000
1!
1&
b1110 I
b1011110 n
#990000
0!
0&
#995000
1!
1&
b1011111 n
b1111 I
#1000000
0!
0&
#1005000
1!
1&
b110 H
0k
1j
b0 I
b1100000 n
#1010000
0!
0&
#1015000
1!
1&
b1100001 n
b1 I
#1020000
0!
0&
#1025000
1!
1&
b10 I
b1100010 n
#1030000
0!
0&
#1035000
1!
1&
b1100011 n
b11 I
#1040000
0!
0&
#1045000
1!
1&
b100 I
b110 o
b0 n
#1050000
0!
0&
#1055000
1!
1&
b1 n
1l
b101 I
1$
#1060000
0!
0&
#1065000
1!
1&
b110 I
b10 n
#1070000
0!
0&
#1075000
1!
1&
b11 n
b111 I
#1080000
0!
0&
#1085000
1!
1&
b1000 I
b100 n
#1090000
0!
0&
#1095000
1!
1&
b101 n
b1001 I
#1100000
0!
0&
#1105000
1!
1&
b1010 I
b110 n
#1110000
0!
0&
#1115000
1!
1&
b111 n
0l
b1011 I
0$
#1120000
0!
0&
#1125000
1!
1&
b1100 I
b1000 n
#1130000
0!
0&
#1135000
1!
1&
b1001 n
b1101 I
#1140000
0!
0&
#1145000
1!
1&
b1110 I
b1010 n
#1150000
0!
0&
#1155000
1!
1&
b1011 n
b1111 I
#1160000
0!
0&
#1165000
1!
1&
b111 H
1k
b0 I
b1100 n
#1170000
0!
0&
#1175000
1!
1&
b1101 n
b1 I
#1180000
0!
0&
#1185000
1!
1&
b10 I
b1110 n
#1190000
0!
0&
#1195000
1!
1&
b1111 n
b11 I
#1200000
0!
0&
#1205000
1!
1&
b100 I
b10000 n
#1210000
0!
0&
#1215000
1!
1&
b10001 n
b101 I
#1220000
0!
0&
#1225000
1!
1&
b110 I
b10010 n
#1230000
0!
0&
#1235000
1!
1&
b10011 n
b111 I
#1240000
0!
0&
#1245000
1!
1&
b1000 I
b10100 n
#1250000
0!
0&
#1255000
1!
1&
b10101 n
b1001 I
#1260000
0!
0&
#1265000
1!
1&
b1010 I
b10110 n
#1270000
0!
0&
#1275000
1!
1&
b10111 n
b1011 I
#1280000
0!
0&
#1285000
1!
1&
b1100 I
b11000 n
#1290000
0!
0&
#1295000
1!
1&
b11001 n
b1101 I
#1300000
0!
0&
#1305000
1!
1&
b1110 I
b11010 n
#1310000
0!
0&
#1315000
1!
1&
b11011 n
b1111 I
#1320000
0!
0&
#1325000
1!
1&
b1000 H
0k
0j
0i
1h
b0 I
b11100 n
#1330000
0!
0&
#1335000
1!
1&
b11101 n
b1 I
#1340000
0!
0&
#1345000
1!
1&
b10 I
b11110 n
#1350000
0!
0&
#1355000
1!
1&
b11111 n
b11 I
#1360000
0!
0&
#1365000
1!
1&
b100 I
b100000 n
#1370000
0!
0&
#1375000
1!
1&
b100001 n
b101 I
#1380000
0!
0&
#1385000
1!
1&
b110 I
b100010 n
#1390000
0!
0&
#1395000
1!
1&
b100011 n
b111 I
#1400000
0!
0&
#1405000
1!
1&
b1000 I
b100100 n
#1410000
0!
0&
#1415000
1!
1&
b100101 n
b1001 I
#1420000
0!
0&
#1425000
1!
1&
b1010 I
b100110 n
#1430000
0!
0&
#1435000
1!
1&
b100111 n
b1011 I
#1440000
0!
0&
#1445000
1!
1&
b1100 I
b101000 n
#1450000
0!
0&
#1455000
1!
1&
b101001 n
b1101 I
#1460000
0!
0&
#1465000
1!
1&
b1110 I
b101010 n
#1470000
0!
0&
#1475000
1!
1&
b101011 n
b1111 I
#1480000
0!
0&
#1485000
1!
1&
b1001 H
1k
b0 I
b101100 n
#1490000
0!
0&
#1495000
1!
1&
b101101 n
b1 I
#1500000
0!
0&
#1505000
1!
1&
b10 I
b101110 n
#1510000
0!
0&
#1515000
1!
1&
b101111 n
b11 I
#1520000
0!
0&
#1525000
1!
1&
b100 I
b110000 n
#1530000
0!
0&
#1535000
1!
1&
b110001 n
b101 I
#1540000
0!
0&
#1545000
1!
1&
b110 I
b110010 n
#1550000
0!
0&
#1555000
1!
1&
b110011 n
b111 I
#1560000
0!
0&
#1565000
1!
1&
b1000 I
b110100 n
#1570000
0!
0&
#1575000
1!
1&
b110101 n
b1001 I
#1580000
0!
0&
#1585000
1!
1&
b1010 I
b110110 n
#1590000
0!
0&
#1595000
1!
1&
b110111 n
b1011 I
#1600000
0!
0&
#1605000
1!
1&
b1100 I
b111000 n
#1610000
0!
0&
#1615000
1!
1&
b111001 n
b1101 I
#1620000
0!
0&
#1625000
1!
1&
b1110 I
b111010 n
#1630000
0!
0&
#1635000
1!
1&
b111011 n
b1111 I
#1640000
0!
0&
#1645000
1!
1&
b1010 H
0k
1j
b0 I
b111100 n
#1650000
0!
0&
#1655000
1!
1&
b111101 n
b1 I
#1660000
0!
0&
#1665000
1!
1&
b10 I
b111110 n
#1670000
0!
0&
#1675000
1!
1&
b111111 n
b11 I
#1680000
0!
0&
#1685000
1!
1&
b100 I
b1000000 n
#1690000
0!
0&
#1695000
1!
1&
b1000001 n
b101 I
#1700000
0!
0&
#1705000
1!
1&
b110 I
b1000010 n
#1710000
0!
0&
#1715000
1!
1&
b1000011 n
b111 I
#1720000
0!
0&
#1725000
1!
1&
b1000 I
b1000100 n
#1730000
0!
0&
#1735000
1!
1&
b1000101 n
b1001 I
#1740000
0!
0&
#1745000
1!
1&
b1010 I
b1000110 n
#1750000
0!
0&
#1755000
1!
1&
b1000111 n
b1011 I
#1760000
0!
0&
#1765000
1!
1&
b1100 I
b1001000 n
#1770000
0!
0&
#1775000
1!
1&
b1001001 n
b1101 I
#1780000
0!
0&
#1785000
1!
1&
b1110 I
b1001010 n
#1790000
0!
0&
#1795000
1!
1&
b1001011 n
b1111 I
#1800000
0!
0&
#1805000
1!
1&
b1011 H
1k
b0 I
b1001100 n
#1810000
0!
0&
#1815000
1!
1&
b1001101 n
b1 I
#1820000
0!
0&
#1825000
1!
1&
b10 I
b1001110 n
#1830000
0!
0&
#1835000
1!
1&
b1001111 n
b11 I
#1840000
0!
0&
#1845000
1!
1&
b100 I
b1010000 n
#1850000
0!
0&
#1855000
1!
1&
b1010001 n
b101 I
#1860000
0!
0&
#1865000
1!
1&
b110 I
b1010010 n
#1870000
0!
0&
#1875000
1!
1&
b1010011 n
b111 I
#1880000
0!
0&
#1885000
1!
1&
b1000 I
b1010100 n
#1890000
0!
0&
#1895000
1!
1&
b1010101 n
b1001 I
#1900000
0!
0&
#1905000
1!
1&
b1010 I
b1010110 n
#1910000
0!
0&
#1915000
1!
1&
b1010111 n
b1011 I
#1920000
0!
0&
#1925000
1!
1&
b1100 I
b1011000 n
#1930000
0!
0&
#1935000
1!
1&
b1011001 n
b1101 I
#1940000
0!
0&
#1945000
1!
1&
b1110 I
b1011010 n
#1950000
0!
0&
#1955000
1!
1&
b1011011 n
b1111 I
#1960000
0!
0&
#1965000
1!
1&
b1100 H
0k
0j
1i
b0 I
b1011100 n
#1970000
0!
0&
#1975000
1!
1&
b1011101 n
b1 I
#1980000
0!
0&
#1985000
1!
1&
b10 I
b1011110 n
#1990000
0!
0&
#1995000
1!
1&
b1011111 n
b11 I
#2000000
0!
0&
#2005000
1!
1&
b100 I
b1100000 n
#2010000
0!
0&
#2015000
1!
1&
b1100001 n
b101 I
#2020000
0!
0&
#2025000
1!
1&
b110 I
b1100010 n
#2030000
0!
0&
#2035000
1!
1&
b1100011 n
b111 I
#2040000
0!
0&
#2045000
1!
1&
b1000 I
b1100 o
b0 n
#2050000
0!
0&
#2055000
1!
1&
b1 n
1l
b1001 I
1$
#2060000
0!
0&
#2065000
1!
1&
b1010 I
b10 n
#2070000
0!
0&
#2075000
1!
1&
b11 n
b1011 I
#2080000
0!
0&
#2085000
1!
1&
b1100 I
b100 n
#2090000
0!
0&
#2095000
1!
1&
b101 n
b1101 I
#2100000
0!
0&
#2105000
1!
1&
b1110 I
b110 n
#2110000
0!
0&
#2115000
1!
1&
b111 n
b1111 I
#2120000
0!
0&
#2125000
1!
1&
b1101 H
1k
b0 I
b1000 n
#2130000
0!
0&
#2135000
1!
1&
b1001 n
b1 I
#2140000
0!
0&
#2145000
1!
1&
b10 I
b1010 n
#2150000
0!
0&
#2155000
1!
1&
b1011 n
b11 I
#2160000
0!
0&
#2165000
1!
1&
b100 I
b1100 n
#2170000
0!
0&
#2175000
1!
1&
b1101 n
0l
b101 I
0$
#2180000
0!
0&
#2185000
1!
1&
b110 I
b1110 n
#2190000
0!
0&
#2195000
1!
1&
b1111 n
b111 I
#2200000
0!
0&
#2205000
1!
1&
b1000 I
b10000 n
#2210000
0!
0&
#2215000
1!
1&
b10001 n
b1001 I
#2220000
0!
0&
#2225000
1!
1&
b1010 I
b10010 n
#2230000
0!
0&
#2235000
1!
1&
b10011 n
b1011 I
#2240000
0!
0&
#2245000
1!
1&
b1100 I
b10100 n
#2250000
0!
0&
#2255000
1!
1&
b10101 n
b1101 I
#2260000
0!
0&
#2265000
1!
1&
b1110 I
b10110 n
#2270000
0!
0&
#2275000
1!
1&
b10111 n
b1111 I
#2280000
0!
0&
#2285000
1!
1&
b1110 H
0k
1j
b0 I
b11000 n
#2290000
0!
0&
#2295000
1!
1&
b11001 n
b1 I
#2300000
0!
0&
#2305000
1!
1&
b10 I
b11010 n
#2310000
0!
0&
#2315000
1!
1&
b11011 n
b11 I
#2320000
0!
0&
#2325000
1!
1&
b100 I
b11100 n
#2330000
0!
0&
#2335000
1!
1&
b11101 n
b101 I
#2340000
0!
0&
#2345000
1!
1&
b110 I
b11110 n
#2350000
0!
0&
#2355000
1!
1&
b11111 n
b111 I
#2360000
0!
0&
#2365000
1!
1&
b1000 I
b100000 n
#2370000
0!
0&
#2375000
1!
1&
b100001 n
b1001 I
#2380000
0!
0&
#2385000
1!
1&
b1010 I
b100010 n
#2390000
0!
0&
#2395000
1!
1&
b100011 n
b1011 I
#2400000
0!
0&
#2405000
1!
1&
b1100 I
b100100 n
#2410000
0!
0&
#2415000
1!
1&
b100101 n
b1101 I
#2420000
0!
0&
#2425000
1!
1&
b1110 I
b100110 n
#2430000
0!
0&
#2435000
1!
1&
b100111 n
b1111 I
#2440000
0!
0&
#2445000
1!
1&
b1111 H
1k
b0 I
b101000 n
#2450000
0!
0&
#2455000
1!
1&
b101001 n
b1 I
#2460000
0!
0&
#2465000
1!
1&
b10 I
b101010 n
#2470000
0!
0&
#2475000
1!
1&
b101011 n
b11 I
#2480000
0!
0&
#2485000
1!
1&
b100 I
b101100 n
#2490000
0!
0&
#2495000
1!
1&
b101101 n
b101 I
#2500000
0!
0&
#2505000
1!
1&
b110 I
b101110 n
#2510000
0!
0&
#2515000
1!
1&
b101111 n
b111 I
#2520000
0!
0&
#2525000
1!
1&
b1000 I
b110000 n
#2530000
0!
0&
#2535000
1!
1&
b110001 n
b1001 I
#2540000
0!
0&
#2545000
1!
1&
b1010 I
b110010 n
#2550000
0!
0&
#2555000
1!
1&
b110011 n
b1011 I
#2560000
0!
0&
#2565000
1!
1&
b1100 I
b110100 n
#2570000
0!
0&
#2575000
1!
1&
b110101 n
b1101 I
#2580000
0!
0&
#2585000
1!
1&
b1110 I
b110110 n
#2590000
0!
0&
#2595000
1!
1&
b110111 n
b1111 I
#2600000
0!
0&
#2605000
1!
1&
b10000 H
0k
0j
0i
0h
1g
b0 I
b111000 n
#2610000
0!
0&
#2615000
1!
1&
b111001 n
b1 I
#2620000
0!
0&
#2625000
1!
1&
b10 I
b111010 n
#2630000
0!
0&
#2635000
1!
1&
b111011 n
b11 I
#2640000
0!
0&
#2645000
1!
1&
b100 I
b111100 n
#2650000
0!
0&
#2655000
1!
1&
b111101 n
b101 I
#2660000
0!
0&
#2665000
1!
1&
b110 I
b111110 n
#2670000
0!
0&
#2675000
1!
1&
b111111 n
b111 I
#2680000
0!
0&
#2685000
1!
1&
b1000 I
b1000000 n
#2690000
0!
0&
#2695000
1!
1&
b1000001 n
b1001 I
#2700000
0!
0&
#2705000
1!
1&
b1010 I
b1000010 n
#2710000
0!
0&
#2715000
1!
1&
b1000011 n
b1011 I
#2720000
0!
0&
#2725000
1!
1&
b1100 I
b1000100 n
#2730000
0!
0&
#2735000
1!
1&
b1000101 n
b1101 I
#2740000
0!
0&
#2745000
1!
1&
b1110 I
b1000110 n
#2750000
0!
0&
#2755000
1!
1&
b1000111 n
b1111 I
#2760000
0!
0&
#2765000
1!
1&
b10001 H
1k
b0 I
b1001000 n
#2770000
0!
0&
#2775000
1!
1&
b1001001 n
b1 I
#2780000
0!
0&
#2785000
1!
1&
b10 I
b1001010 n
#2790000
0!
0&
#2795000
1!
1&
b1001011 n
b11 I
#2800000
0!
0&
#2805000
1!
1&
b100 I
b1001100 n
#2810000
0!
0&
#2815000
1!
1&
b1001101 n
b101 I
#2820000
0!
0&
#2825000
1!
1&
b110 I
b1001110 n
#2830000
0!
0&
#2835000
1!
1&
b1001111 n
b111 I
#2840000
0!
0&
#2845000
1!
1&
b1000 I
b1010000 n
#2850000
0!
0&
#2855000
1!
1&
b1010001 n
b1001 I
#2860000
0!
0&
#2865000
1!
1&
b1010 I
b1010010 n
#2870000
0!
0&
#2875000
1!
1&
b1010011 n
b1011 I
#2880000
0!
0&
#2885000
1!
1&
b1100 I
b1010100 n
#2890000
0!
0&
#2895000
1!
1&
b1010101 n
b1101 I
#2900000
0!
0&
#2905000
1!
1&
b1110 I
b1010110 n
#2910000
0!
0&
#2915000
1!
1&
b1010111 n
b1111 I
#2920000
0!
0&
#2925000
1!
1&
b10010 H
0k
1j
b0 I
b1011000 n
#2930000
0!
0&
#2935000
1!
1&
b1011001 n
b1 I
#2940000
0!
0&
#2945000
1!
1&
b10 I
b1011010 n
#2950000
0!
0&
#2955000
1!
1&
b1011011 n
b11 I
#2960000
0!
0&
#2965000
1!
1&
b100 I
b1011100 n
#2970000
0!
0&
#2975000
1!
1&
b1011101 n
b101 I
#2980000
0!
0&
#2985000
1!
1&
b110 I
b1011110 n
#2990000
0!
0&
#2995000
1!
1&
b1011111 n
b111 I
#3000000
0!
0&
#3005000
1!
1&
b1000 I
b1100000 n
#3010000
0!
0&
#3015000
1!
1&
b1100001 n
b1001 I
#3020000
0!
0&
#3025000
1!
1&
b1010 I
b1100010 n
#3030000
0!
0&
#3035000
1!
1&
b1100011 n
b1011 I
#3040000
0!
0&
#3045000
1!
1&
b1100 I
b10010 o
b0 n
#3050000
0!
0&
#3055000
1!
1&
b1 n
1l
b1101 I
1$
#3060000
0!
0&
#3065000
1!
1&
b1110 I
b10 n
#3070000
0!
0&
#3075000
1!
1&
b11 n
b1111 I
#3080000
0!
0&
#3085000
1!
1&
b10011 H
1k
b0 I
b100 n
#3090000
0!
0&
#3095000
1!
1&
b101 n
b1 I
#3100000
0!
0&
#3105000
1!
1&
b10 I
b110 n
#3110000
0!
0&
#3115000
1!
1&
b111 n
b11 I
#3120000
0!
0&
#3125000
1!
1&
b100 I
b1000 n
#3130000
0!
0&
#3135000
1!
1&
b1001 n
b101 I
#3140000
0!
0&
#3145000
1!
1&
b110 I
b1010 n
#3150000
0!
0&
#3155000
1!
1&
b1011 n
b111 I
#3160000
0!
0&
#3165000
1!
1&
b1000 I
b1100 n
#3170000
0!
0&
#3175000
1!
1&
b1101 n
b1001 I
#3180000
0!
0&
#3185000
1!
1&
b1010 I
b1110 n
#3190000
0!
0&
#3195000
1!
1&
b1111 n
b1011 I
#3200000
0!
0&
#3205000
1!
1&
b1100 I
b10000 n
#3210000
0!
0&
#3215000
1!
1&
b10001 n
b1101 I
#3220000
0!
0&
#3225000
1!
1&
b1110 I
b10010 n
#3230000
0!
0&
#3235000
1!
1&
b10011 n
0l
b1111 I
0$
#3240000
0!
0&
#3245000
1!
1&
b10100 H
0k
0j
1i
b0 I
b10100 n
#3250000
0!
0&
#3255000
1!
1&
b10101 n
b1 I
#3260000
0!
0&
#3265000
1!
1&
b10 I
b10110 n
#3270000
0!
0&
#3275000
1!
1&
b10111 n
b11 I
#3280000
0!
0&
#3285000
1!
1&
b100 I
b11000 n
#3290000
0!
0&
#3295000
1!
1&
b11001 n
b101 I
#3300000
0!
0&
#3305000
1!
1&
b110 I
b11010 n
#3310000
0!
0&
#3315000
1!
1&
b11011 n
b111 I
#3320000
0!
0&
#3325000
1!
1&
b1000 I
b11100 n
#3330000
0!
0&
#3335000
1!
1&
b11101 n
b1001 I
#3340000
0!
0&
#3345000
1!
1&
b1010 I
b11110 n
#3350000
0!
0&
#3355000
1!
1&
b11111 n
b1011 I
#3360000
0!
0&
#3365000
1!
1&
b1100 I
b100000 n
#3370000
0!
0&
#3375000
1!
1&
b100001 n
b1101 I
#3380000
0!
0&
#3385000
1!
1&
b1110 I
b100010 n
#3390000
0!
0&
#3395000
1!
1&
b100011 n
b1111 I
#3400000
0!
0&
#3405000
1!
1&
b10101 H
1k
b0 I
b100100 n
#3410000
0!
0&
#3415000
1!
1&
b100101 n
b1 I
#3420000
0!
0&
#3425000
1!
1&
b10 I
b100110 n
#3430000
0!
0&
#3435000
1!
1&
b100111 n
b11 I
#3440000
0!
0&
#3445000
1!
1&
b100 I
b101000 n
#3450000
0!
0&
#3455000
1!
1&
b101001 n
b101 I
#3460000
0!
0&
#3465000
1!
1&
b110 I
b101010 n
#3470000
0!
0&
#3475000
1!
1&
b101011 n
b111 I
#3480000
0!
0&
#3485000
1!
1&
b1000 I
b101100 n
#3490000
0!
0&
#3495000
1!
1&
b101101 n
b1001 I
#3500000
0!
0&
#3505000
1!
1&
b1010 I
b101110 n
#3510000
0!
0&
#3515000
1!
1&
b101111 n
b1011 I
#3520000
0!
0&
