PWM_LED_Chaser/PWM_LED_Chaser.srcs/sources_1/imports/PWM_LED_Chaser/pwm_generator.v
module pwm_generator #(
	//parameter DUTYCYCLE = 70, //MUST BE an Integer between 0 and the period
	parameter PERIOD = 1000 //MUST BE AN INTEGER GREATER THAN 1. Is number of base clk cycles in a period
)(
	input clk,
	input rst_n,
	input [31:0] duty,
	output reg out,
	output reg error
);
	// Runs once at time 0 in simulation, before any clock edge.
	// PERIOD is a parameter, so this condition is fully determined
	// at elaboration — the check costs zero hardware.
	initial begin
		if (PERIOD < 2) begin
			// %m expands to the full hierarchical instance path, so you
			// find out *which* instantiation was misparameterised.
			// %0d prints the integer with no padding.
			$display("%m: PERIOD must be >= 2, got %0d", PERIOD);
			$finish;
		end
	end

	reg [31:0] counter;
	reg [31:0] duty_D;

	always @(posedge clk) begin
		if (!rst_n) begin
			out <= 1'b0;
			error <= 1'b0;
			counter <= 32'b0;
			duty_D <= 0;
		end else begin
			if (duty_D>PERIOD) begin
				error <= 1'b1;
			end else begin
				error <= 1'b0;
			end

			if (counter == PERIOD - 1) begin
				duty_D <= duty;
				counter <= 32'b0;
			end else begin
				counter <= counter + 1'b1;
			end
			if (counter>=duty_D) begin	
					out <= 1'b0;
			end else begin
				out <= 1'b1;
			end
		end
	end
endmodule

pwm_gen_tb.v
`timescale 1ms/1us

module pwm_gen_tb;

    reg clk;
    reg rst_n;
    reg [31:0] duty;
    wire out;
    wire error;

    pwm_generator #() dut (
        .clk        (clk),
    	.rst_n      (rst_n),
    	.duty       (duty),
    	.out        (out),
    	.error      (error)
    );

    initial clk = 1'b0;
    always #5 clk = ~clk;

    initial begin
        // Dump waveforms for GTKWave / your viewer of choice
        $dumpfile("pwm_gen_tb.vcd");
        $dumpvars(0, pwm_gen_tb);

        rst_n = 1'b0;
        duty = 32'b0;
        #30
        rst_n = 1'b1;
        duty = 32'd50;
        #10000
        duty = 32'd90;
        #10000
        duty = 32'd10;
        #10000
        $finish;
    end
endmodule

pwm_gen_tb.vcd
$date
	Wed Jul 29 20:51:16 2026
$end
$version
	Questa Altera Starter FPGA Edition Version 2025.2
$end
$timescale
	1us
$end

$scope module pwm_gen_tb $end
$var reg 1 ! clk $end
$var reg 1 " rst_n $end
$var reg 32 # duty [31:0] $end
$var wire 1 $ out $end
$var wire 1 % error $end

$scope module dut $end
$var parameter 32 & PERIOD $end
$var wire 1 ' clk $end
$var wire 1 ( rst_n $end
$var wire 1 ) duty [31] $end
$var wire 1 * duty [30] $end
$var wire 1 + duty [29] $end
$var wire 1 , duty [28] $end
$var wire 1 - duty [27] $end
$var wire 1 . duty [26] $end
$var wire 1 / duty [25] $end
$var wire 1 0 duty [24] $end
$var wire 1 1 duty [23] $end
$var wire 1 2 duty [22] $end
$var wire 1 3 duty [21] $end
$var wire 1 4 duty [20] $end
$var wire 1 5 duty [19] $end
$var wire 1 6 duty [18] $end
$var wire 1 7 duty [17] $end
$var wire 1 8 duty [16] $end
$var wire 1 9 duty [15] $end
$var wire 1 : duty [14] $end
$var wire 1 ; duty [13] $end
$var wire 1 < duty [12] $end
$var wire 1 = duty [11] $end
$var wire 1 > duty [10] $end
$var wire 1 ? duty [9] $end
$var wire 1 @ duty [8] $end
$var wire 1 A duty [7] $end
$var wire 1 B duty [6] $end
$var wire 1 C duty [5] $end
$var wire 1 D duty [4] $end
$var wire 1 E duty [3] $end
$var wire 1 F duty [2] $end
$var wire 1 G duty [1] $end
$var wire 1 H duty [0] $end
$var reg 1 I out $end
$var reg 1 J error $end
$var reg 32 K counter [31:0] $end
$var reg 32 L duty_D [31:0] $end
$upscope $end
$upscope $end
$enddefinitions $end
#0
$dumpvars
0!
0"
b0 #
xI
xJ
bx K
bx L
b1100100 &
x$
x%
0H
0G
0F
0E
0D
0C
0B
0A
0@
0?
0>
0=
0<
0;
0:
09
08
07
06
05
04
03
02
01
00
0/
0.
0-
0,
0+
0*
0)
0(
0'
$end
#5000
1!
1'
0I
0J
b0 K
b0 L
0$
0%
#10000
0!
0'
#15000
1!
1'
#20000
0!
0'
#25000
1!
1'
#30000
1"
b110010 #
0!
1(
1G
1D
1C
0'
#35000
1!
1'
b1 K
#40000
0!
0'
#45000
1!
1'
b10 K
#50000
0!
0'
#55000
1!
1'
b11 K
#60000
0!
0'
#65000
1!
1'
b100 K
#70000
0!
0'
#75000
1!
1'
b101 K
#80000
0!
0'
#85000
1!
1'
b110 K
#90000
0!
0'
#95000
1!
1'
b111 K
#100000
0!
0'
#105000
1!
1'
b1000 K
#110000
0!
0'
#115000
1!
1'
b1001 K
#120000
0!
0'
#125000
1!
1'
b1010 K
#130000
0!
0'
#135000
1!
1'
b1011 K
#140000
0!
0'
#145000
1!
1'
b1100 K
#150000
0!
0'
#155000
1!
1'
b1101 K
#160000
0!
0'
#165000
1!
1'
b1110 K
#170000
0!
0'
#175000
1!
1'
b1111 K
#180000
0!
0'
#185000
1!
1'
b10000 K
#190000
0!
0'
#195000
1!
1'
b10001 K
#200000
0!
0'
#205000
1!
1'
b10010 K
#210000
0!
0'
#215000
1!
1'
b10011 K
#220000
0!
0'
#225000
1!
1'
b10100 K
#230000
0!
0'
#235000
1!
1'
b10101 K
#240000
0!
0'
#245000
1!
1'
b10110 K
#250000
0!
0'
#255000
1!
1'
b10111 K
#260000
0!
0'
#265000
1!
1'
b11000 K
#270000
0!
0'
#275000
1!
1'
b11001 K
#280000
0!
0'
#285000
1!
1'
b11010 K
#290000
0!
0'
#295000
1!
1'
b11011 K
#300000
0!
0'
#305000
1!
1'
b11100 K
#310000
0!
0'
#315000
1!
1'
b11101 K
#320000
0!
0'
#325000
1!
1'
b11110 K
#330000
0!
0'
#335000
1!
1'
b11111 K
#340000
0!
0'
#345000
1!
1'
b100000 K
#350000
0!
0'
#355000
1!
1'
b100001 K
#360000
0!
0'
#365000
1!
1'
b100010 K
#370000
0!
0'
#375000
1!
1'
b100011 K
#380000
0!
0'
#385000
1!
1'
b100100 K
#390000
0!
0'
#395000
1!
1'
b100101 K
#400000
0!
0'
#405000
1!
1'
b100110 K
#410000
0!
0'
#415000
1!
1'
b100111 K
#420000
0!
0'
#425000
1!
1'
b101000 K
#430000
0!
0'
#435000
1!
1'
b101001 K
#440000
0!
0'
#445000
1!
1'
b101010 K
#450000
0!
0'
#455000
1!
1'
b101011 K
#460000
0!
0'
#465000
1!
1'
b101100 K
#470000
0!
0'
#475000
1!
1'
b101101 K
#480000
0!
0'
#485000
1!
1'
b101110 K
#490000
0!
0'
#495000
1!
1'
b101111 K
#500000
0!
0'
#505000
1!
1'
b110000 K
#510000
0!
0'
#515000
1!
1'
b110001 K
#520000
0!
0'
#525000
1!
1'
b110010 K
#530000
0!
0'
#535000
1!
1'
b110011 K
#540000
0!
0'
#545000
1!
1'
b110100 K
#550000
0!
0'
#555000
1!
1'
b110101 K
#560000
0!
0'
#565000
1!
1'
b110110 K
#570000
0!
0'
#575000
1!
1'
b110111 K
#580000
0!
0'
#585000
1!
1'
b111000 K
#590000
0!
0'
#595000
1!
1'
b111001 K
#600000
0!
0'
#605000
1!
1'
b111010 K
#610000
0!
0'
#615000
1!
1'
b111011 K
#620000
0!
0'
#625000
1!
1'
b111100 K
#630000
0!
0'
#635000
1!
1'
b111101 K
#640000
0!
0'
#645000
1!
1'
b111110 K
#650000
0!
0'
#655000
1!
1'
b111111 K
#660000
0!
0'
#665000
1!
1'
b1000000 K
#670000
0!
0'
#675000
1!
1'
b1000001 K
#680000
0!
0'
#685000
1!
1'
b1000010 K
#690000
0!
0'
#695000
1!
1'
b1000011 K
#700000
0!
0'
#705000
1!
1'
b1000100 K
#710000
0!
0'
#715000
1!
1'
b1000101 K
#720000
0!
0'
#725000
1!
1'
b1000110 K
#730000
0!
0'
#735000
1!
1'
b1000111 K
#740000
0!
0'
#745000
1!
1'
b1001000 K
#750000
0!
0'
#755000
1!
1'
b1001001 K
#760000
0!
0'
#765000
1!
1'
b1001010 K
#770000
0!
0'
#775000
1!
1'
b1001011 K
#780000
0!
0'
#785000
1!
1'
b1001100 K
#790000
0!
0'
#795000
1!
1'
b1001101 K
#800000
0!
0'
#805000
1!
1'
b1001110 K
#810000
0!
0'
#815000
1!
1'
b1001111 K
#820000
0!
0'
#825000
1!
1'
b1010000 K
#830000
0!
0'
#835000
1!
1'
b1010001 K
#840000
0!
0'
#845000
1!
1'
b1010010 K
#850000
0!
0'
#855000
1!
1'
b1010011 K
#860000
0!
0'
#865000
1!
1'
b1010100 K
#870000
0!
0'
#875000
1!
1'
b1010101 K
#880000
0!
0'
#885000
1!
1'
b1010110 K
#890000
0!
0'
#895000
1!
1'
b1010111 K
#900000
0!
0'
#905000
1!
1'
b1011000 K
#910000
0!
0'
#915000
1!
1'
b1011001 K
#920000
0!
0'
#925000
1!
1'
b1011010 K
#930000
0!
0'
#935000
1!
1'
b1011011 K
#940000
0!
0'
#945000
1!
1'
b1011100 K
#950000
0!
0'
#955000
1!
1'
b1011101 K
#960000
0!
0'
#965000
1!
1'
b1011110 K
#970000
0!
0'
#975000
1!
1'
b1011111 K
#980000
0!
0'
#985000
1!
1'
b1100000 K
#990000
0!
0'
#995000
1!
1'
b1100001 K
#1000000
0!
0'
#1005000
1!
1'
b1100010 K
#1010000
0!
0'
#1015000
1!
1'
b1100011 K
#1020000
0!
0'
#1025000
1!
1'
b110010 L
b0 K
#1030000
0!
0'
#1035000
1!
1'
b1 K
1I
1$
#1040000
0!
0'
#1045000
1!
1'
b10 K
#1050000
0!
0'
#1055000
1!
1'
b11 K
#1060000
0!
0'
#1065000
1!
1'
b100 K
#1070000
0!
0'
#1075000
1!
1'
b101 K
#1080000
0!
0'
#1085000
1!
1'
b110 K
#1090000
0!
0'
#1095000
1!
1'
b111 K
#1100000
0!
0'
#1105000
1!
1'
b1000 K
#1110000
0!
0'
#1115000
1!
1'
b1001 K
#1120000
0!
0'
#1125000
1!
1'
b1010 K
#1130000
0!
0'
#1135000
1!
1'
b1011 K
#1140000
0!
0'
#1145000
1!
1'
b1100 K
#1150000
0!
0'
#1155000
1!
1'
b1101 K
#1160000
0!
0'
#1165000
1!
1'
b1110 K
#1170000
0!
0'
#1175000
1!
1'
b1111 K
#1180000
0!
0'
#1185000
1!
1'
b10000 K
#1190000
0!
0'
#1195000
1!
1'
b10001 K
#1200000
0!
0'
#1205000
1!
1'
b10010 K
#1210000
0!
0'
#1215000
1!
1'
b10011 K
#1220000
0!
0'
#1225000
1!
1'
b10100 K
#1230000
0!
0'
#1235000
1!
1'
b10101 K
#1240000
0!
0'
#1245000
1!
1'
b10110 K
#1250000
0!
0'
#1255000
1!
1'
b10111 K
#1260000
0!
0'
#1265000
1!
1'
b11000 K
#1270000
0!
0'
#1275000
1!
1'
b11001 K
#1280000
0!
0'
#1285000
1!
1'
b11010 K
#1290000
0!
0'
#1295000
1!
1'
b11011 K
#1300000
0!
0'
#1305000
1!
1'
b11100 K
#1310000
0!
0'
#1315000
1!
1'
b11101 K
#1320000
0!
0'
#1325000
1!
1'
b11110 K
#1330000
0!
0'
#1335000
1!
1'
b11111 K
#1340000
0!
0'
#1345000
1!
1'
b100000 K
#1350000
0!
0'
#1355000
1!
1'
b100001 K
#1360000
0!
0'
#1365000
1!
1'
b100010 K
#1370000
0!
0'
#1375000
1!
1'
b100011 K
#1380000
0!
0'
#1385000
1!
1'
b100100 K
#1390000
0!
0'
#1395000
1!
1'
b100101 K
#1400000
0!
0'
#1405000
1!
1'
b100110 K
#1410000
0!
0'
#1415000
1!
1'
b100111 K
#1420000
0!
0'
#1425000
1!
1'
b101000 K
#1430000
0!
0'
#1435000
1!
1'
b101001 K
#1440000
0!
0'
#1445000
1!
1'
b101010 K
#1450000
0!
0'
#1455000
1!
1'
b101011 K
#1460000
0!
0'
#1465000
1!
1'
b101100 K
#1470000
0!
0'
#1475000
1!
1'
b101101 K
#1480000
0!
0'
#1485000
1!
1'
b101110 K
#1490000
0!
0'
#1495000
1!
1'
b101111 K
#1500000
0!
0'
#1505000
1!
1'
b110000 K
#1510000
0!
0'
#1515000
1!
1'
b110001 K
#1520000
0!
0'
#1525000
1!
1'
b110010 K
#1530000
0!
0'
#1535000
1!
1'
b110011 K
0I
0$
#1540000
0!
0'
#1545000
1!
1'
b110100 K
#1550000
0!
0'
#1555000
1!
1'
b110101 K
#1560000
0!
0'
#1565000
1!
1'
b110110 K
#1570000
0!
0'
#1575000
1!
1'
b110111 K
#1580000
0!
0'
#1585000
1!
1'
b111000 K
#1590000
0!
0'
#1595000
1!
1'
b111001 K
#1600000
0!
0'
#1605000
1!
1'
b111010 K
#1610000
0!
0'
#1615000
1!
1'
b111011 K
#1620000
0!
0'
#1625000
1!
1'
b111100 K
#1630000
0!
0'
#1635000
1!
1'
b111101 K
#1640000
0!
0'
#1645000
1!
1'
b111110 K
#1650000
0!
0'
#1655000
1!
1'
b111111 K
#1660000
0!
0'
#1665000
1!
1'
b1000000 K
#1670000
0!
0'
#1675000
1!
1'
b1000001 K
#1680000
0!
0'
#1685000
1!
1'
b1000010 K
#1690000
0!
0'
#1695000
1!
1'
b1000011 K
#1700000
0!
0'
#1705000
1!
1'
b1000100 K
#1710000
0!
0'
#1715000
1!
1'
b1000101 K
#1720000
0!
0'
#1725000
1!
1'
b1000110 K
#1730000
0!
0'
#1735000
1!
1'
b1000111 K
#1740000
0!
0'
#1745000
1!
1'
b1001000 K
#1750000
0!
0'
#1755000
1!
1'
b1001001 K
#1760000
0!
0'
#1765000
1!
1'
b1001010 K
#1770000
0!
0'
#1775000
1!
1'
b1001011 K
#1780000
0!
0'
#1785000
1!
1'
b1001100 K
#1790000
0!
0'
#1795000
1!
1'
b1001101 K
#1800000
0!
0'
#1805000
1!
1'
b1001110 K
#1810000
0!
0'
#1815000
1!
1'
b1001111 K
#1820000
0!
0'
#1825000
1!
1'
b1010000 K
#1830000
0!
0'
#1835000
1!
1'
b1010001 K
#1840000
0!
0'
#1845000
1!
1'
b1010010 K
#1850000
0!
0'
#1855000
1!
1'
b1010011 K
#1860000
0!
0'
#1865000
1!
1'
b1010100 K
#1870000
0!
0'
#1875000
1!
1'
b1010101 K
#1880000
0!
0'
#1885000
1!
1'
b1010110 K
#1890000
0!
0'
#1895000
1!
1'
b1010111 K
#1900000
0!
0'
#1905000
1!
1'
b1011000 K
#1910000
0!
0'
#1915000
1!
1'
b1011001 K
#1920000
0!
0'
#1925000
1!
1'
b1011010 K
#1930000
0!
0'
#1935000
1!
1'
b1011011 K
#1940000
0!
0'
#1945000
1!
1'
b1011100 K
#1950000
0!
0'
#1955000
1!
1'
b1011101 K
#1960000
0!
0'
#1965000
1!
1'
b1011110 K
#1970000
0!
0'
#1975000
1!
1'
b1011111 K
#1980000
0!
0'
#1985000
1!
1'
b1100000 K
#1990000
0!
0'
#1995000
1!
1'
b1100001 K
#2000000
0!
0'
#2005000
1!
1'
b1100010 K
#2010000
0!
0'
#2015000
1!
1'
b1100011 K
#2020000
0!
0'
#2025000
1!
1'
b0 K
#2030000
0!
0'
#2035000
1!
1'
b1 K
1I
1$
#2040000
0!
0'
#2045000
1!
1'
b10 K
#2050000
0!
0'
#2055000
1!
1'
b11 K
#2060000
0!
0'
#2065000
1!
1'
b100 K
#2070000
0!
0'
#2075000
1!
1'
b101 K
#2080000
0!
0'
#2085000
1!
1'
b110 K
#2090000
0!
0'
#2095000
1!
1'
b111 K
#2100000
0!
0'
#2105000
1!
1'
b1000 K
#2110000
0!
0'
#2115000
1!
1'
b1001 K
#2120000
0!
0'
#2125000
1!
1'
b1010 K
#2130000
0!
0'
#2135000
1!
1'
b1011 K
#2140000
0!
0'
#2145000
1!
1'
b1100 K
#2150000
0!
0'
#2155000
1!
1'
b1101 K
#2160000
0!
0'
#2165000
1!
1'
b1110 K
#2170000
0!
0'
#2175000
1!
1'
b1111 K
#2180000
0!
0'
#2185000
1!
1'
b10000 K
#2190000
0!
0'
#2195000
1!
1'
b10001 K
#2200000
0!
0'
#2205000
1!
1'
b10010 K
#2210000
0!
0'
#2215000
1!
1'
b10011 K
#2220000
0!
0'
#2225000
1!
1'
b10100 K
#2230000
0!
0'
#2235000
1!
1'
b10101 K
#2240000
0!
0'
#2245000
1!
1'
b10110 K
#2250000
0!
0'
#2255000
1!
1'
b10111 K
#2260000
0!
0'
#2265000
1!
1'
b11000 K
#2270000
0!
0'
#2275000
1!
1'
b11001 K
#2280000
0!
0'
#2285000
1!
1'
b11010 K
#2290000
0!
0'
#2295000
1!
1'
b11011 K
#2300000
0!
0'
#2305000
1!
1'
b11100 K
#2310000
0!
0'
#2315000
1!
1'
b11101 K
#2320000
0!
0'
#2325000
1!
1'
b11110 K
#2330000
0!
0'
#2335000
1!
1'
b11111 K
#2340000
0!
0'
#2345000
1!
1'
b100000 K
#2350000
0!
0'
#2355000
1!
1'
b100001 K
#2360000
0!
0'
#2365000
1!
1'
b100010 K
#2370000
0!
0'
#2375000
1!
1'
b100011 K
#2380000
0!
0'
#2385000
1!
1'
b100100 K
#2390000
0!
0'
#2395000
1!
1'
b100101 K
#2400000
0!
0'
#2405000
1!
1'
b100110 K
#2410000
0!
0'
#2415000
1!
1'
b100111 K
#2420000
0!
0'
#2425000
1!
1'
b101000 K
#2430000
0!
0'
#2435000
1!
1'
b101001 K
#2440000
0!
0'
#2445000
1!
1'
b101010 K
#2450000
0!
0'
#2455000
1!
1'
b101011 K
#2460000
0!
0'
#2465000
1!
1'
b101100 K
#2470000
0!
0'
#2475000
1!
1'
b101101 K
#2480000
0!
0'
#2485000
1!
1'
b101110 K
#2490000
0!
0'
#2495000
1!
1'
b101111 K
#2500000
0!
0'
#2505000
1!
1'
b110000 K
#2510000
0!
0'
#2515000
1!
1'
b110001 K
#2520000
0!
0'
#2525000
1!
1'
b110010 K
#2530000
0!
0'
#2535000
1!
1'
b110011 K
0I
0$
#2540000
0!
0'
#2545000
1!
1'
b110100 K
#2550000
0!
0'
#2555000
1!
1'
b110101 K
#2560000
0!
0'
#2565000
1!
1'
b110110 K
#2570000
0!
0'
#2575000
1!
1'
b110111 K
#2580000
0!
0'
#2585000
1!
1'
b111000 K
#2590000
0!
0'
#2595000
1!
1'
b111001 K
#2600000
0!
0'
#2605000
1!
1'
b111010 K
#2610000
0!
0'
#2615000
1!
1'
b111011 K
#2620000
0!
0'
#2625000
1!
1'
b111100 K
#2630000
0!
0'
#2635000
1!
1'
b111101 K
#2640000
0!
0'
#2645000
1!
1'
b111110 K
#2650000
0!
0'
#2655000
1!
1'
b111111 K
#2660000
0!
0'
#2665000
1!
1'
b1000000 K
#2670000
0!
0'
#2675000
1!
1'
b1000001 K
#2680000
0!
0'
#2685000
1!
1'
b1000010 K
#2690000
0!
0'
#2695000
1!
1'
b1000011 K
#2700000
0!
0'
#2705000
1!
1'
b1000100 K
#2710000
0!
0'
#2715000
1!
1'
b1000101 K
#2720000
0!
0'
#2725000
1!
1'
b1000110 K
#2730000
0!
0'
#2735000
1!
1'
b1000111 K
#2740000
0!
0'
#2745000
1!
1'
b1001000 K
#2750000
0!
0'
#2755000
1!
1'
b1001001 K
#2760000
0!
0'
#2765000
1!
1'
b1001010 K
#2770000
0!
0'
#2775000
1!
1'
b1001011 K
#2780000
0!
0'
#2785000
1!
1'
b1001100 K
#2790000
0!
0'
#2795000
1!
1'
b1001101 K
#2800000
0!
0'
#2805000
1!
1'
b1001110 K
#2810000
0!
0'
#2815000
1!
1'
b1001111 K
#2820000
0!
0'
#2825000
1!
1'
b1010000 K
#2830000
0!
0'
#2835000
1!
1'
b1010001 K
#2840000
0!
0'
#2845000
1!
1'
b1010010 K
#2850000
0!
0'
#2855000
1!
1'
b1010011 K
#2860000
0!
0'
#2865000
1!
1'
b1010100 K
#2870000
0!
0'
#2875000
1!
1'
b1010101 K
#2880000
0!
0'
#2885000
1!
1'
b1010110 K
#2890000
0!
0'
#2895000
1!
1'
b1010111 K
#2900000
0!
0'
#2905000
1!
1'
b1011000 K
#2910000
0!
0'
#2915000
1!
1'
b1011001 K
#2920000
0!
0'
#2925000
1!
1'
b1011010 K
#2930000
0!
0'
#2935000
1!
1'
b1011011 K
#2940000
0!
0'
#2945000
1!
1'
b1011100 K
#2950000
0!
0'
#2955000
1!
1'
b1011101 K
#2960000
0!
0'
#2965000
1!
1'
b1011110 K
#2970000
0!
0'
#2975000
1!
1'
b1011111 K
#2980000
0!
0'
#2985000
1!
1'
b1100000 K
#2990000
0!
0'
#2995000
1!
1'
b1100001 K
#3000000
0!
0'
#3005000
1!
1'
b1100010 K
#3010000
0!
0'
#3015000
1!
1'
b1100011 K
#3020000
0!
0'
#3025000
1!
1'
b0 K
#3030000
0!
0'
#3035000
1!
1'
b1 K
1I
1$
#3040000
0!
0'
#3045000
1!
1'
b10 K
#3050000
0!
0'
#3055000
1!
1'
b11 K
#3060000
0!
0'
#3065000
1!
1'
b100 K
#3070000
0!
0'
#3075000
1!
1'
b101 K
#3080000
0!
0'
#3085000
1!
1'
b110 K
#3090000
0!
0'
#3095000
1!
1'
b111 K
#3100000
0!
0'
#3105000
1!
1'
b1000 K
#3110000
0!
0'
#3115000
1!
1'
b1001 K
#3120000
0!
0'
#3125000
1!
1'
b1010 K
#3130000
0!
0'
#3135000
1!
1'
b1011 K
#3140000
0!
0'
#3145000
1!
1'
b1100 K
#3150000
0!
0'
#3155000
1!
1'
b1101 K
#3160000
0!
0'
#3165000
1!
1'
b1110 K
#3170000
0!
0'
#3175000
1!
1'
b1111 K
#3180000
0!
0'
#3185000
1!
1'
b10000 K
#3190000
0!
0'
#3195000
1!
1'
b10001 K
#3200000
0!
0'
#3205000
1!
1'
b10010 K
#3210000
0!
0'
#3215000
1!
1'
b10011 K
#3220000
0!
0'
#3225000
1!
1'
b10100 K
#3230000
0!
0'
#3235000
1!
1'
b10101 K
#3240000
0!
0'
#3245000
1!
1'
b10110 K
#3250000
0!
0'
#3255000
1!
1'
b10111 K
#3260000
0!
0'
#3265000
1!
1'
b11000 K
#3270000
0!
0'
#3275000
1!
1'
b11001 K
#3280000
0!
0'
#3285000
1!
1'
b11010 K
#3290000
0!
0'
#3295000
1!
1'
b11011 K
#3300000
0!
0'
#3305000
1!
1'
b11100 K
#3310000
0!
0'
#3315000
1!
1'
b11101 K
#3320000
0!
0'
#3325000
1!
1'
b11110 K
#3330000
0!
0'
#3335000
1!
1'
b11111 K
#3340000
0!
0'
#3345000
1!
1'
b100000 K
#3350000
0!
0'
#3355000
1!
1'
b100001 K
#3360000
0!
0'
#3365000
1!
1'
b100010 K
#3370000
0!
0'
#3375000
1!
1'
b100011 K
#3380000
0!
0'
#3385000
1!
1'
b100100 K
#3390000
0!
0'
#3395000
1!
1'
b100101 K
#3400000
0!
0'
#3405000
1!
1'
b100110 K
#3410000
0!
0'
#3415000
1!
1'
b100111 K
#3420000
0!
0'
#3425000
1!
1'
b101000 K
#3430000
0!
0'
#3435000
1!
1'
b101001 K
#3440000
0!
0'
#3445000
1!
1'
b101010 K
#3450000
0!
0'
#3455000
1!
1'
b101011 K
#3460000
0!
0'
#3465000
1!
1'
b101100 K
#3470000
0!
0'
#3475000
1!
1'
b101101 K
#3480000
0!
0'
#3485000
1!
1'
b101110 K
#3490000
0!
0'
#3495000
1!
1'
b101111 K
#3500000
0!
0'
#3505000
1!
1'
b110000 K
#3510000
0!
0'
#3515000
1!
1'
b110001 K
#3520000
0!
0'
#3525000
1!
1'
b110010 K
#3530000
0!
0'
#3535000
1!
1'
b110011 K
0I
0$
#3540000
0!
0'
#3545000
1!
1'
b110100 K
#3550000
0!
0'
#3555000
1!
1'
b110101 K
#3560000
0!
0'
#3565000
1!
1'
b110110 K
#3570000
0!
0'
#3575000
1!
1'
b110111 K
#3580000
0!
0'
#3585000
1!
1'
b111000 K
#3590000
0!
0'
#3595000
1!
1'
b111001 K
#3600000
0!
0'
#3605000
1!
1'
b111010 K
#3610000
0!
0'
#3615000
1!
1'
b111011 K
#3620000
0!
0'
#3625000
1!
1'
b111100 K
#3630000
0!
0'
#3635000
1!
1'
b111101 K
#3640000
0!
0'
#3645000
1!
1'
b111110 K
#3650000
0!
0'
#3655000
1!
1'
b111111 K
#3660000
0!
0'
#3665000
1!
1'
b1000000 K
#3670000
0!
0'
#3675000
1!
1'
b1000001 K
#3680000
0!
0'
#3685000
1!
1'
b1000010 K
#3690000
0!
0'
#3695000
1!
1'
b1000011 K
#3700000
0!
0'
#3705000
1!
1'
b1000100 K
#3710000
0!
0'
#3715000
1!
1'
b1000101 K
#3720000
0!
0'
#3725000
1!
1'
b1000110 K
#3730000
0!
0'
#3735000
1!
1'
b1000111 K
#3740000
0!
0'
#3745000
1!
1'
b1001000 K
#3750000
0!
0'
#3755000
1!
1'
b1001001 K
#3760000
0!
0'
#3765000
1!
1'
b1001010 K
#3770000
0!
0'
#3775000
1!
1'
b1001011 K
#3780000
0!
0'
#3785000
1!
1'
b1001100 K
#3790000
0!
0'
#3795000
1!
1'
b1001101 K
#3800000
0!
0'
#3805000
1!
1'
b1001110 K
#3810000
0!
0'
#3815000
1!
1'
b1001111 K
#3820000
0!
0'
#3825000
1!
1'
b1010000 K
#3830000
0!
0'
#3835000
1!
1'
b1010001 K
#3840000
0!
0'
#3845000
1!
1'
b1010010 K
#3850000
0!
0'
#3855000
1!
1'
b1010011 K
#3860000
0!
0'
#3865000
1!
1'
b1010100 K
#3870000
0!
0'
#3875000
1!
1'
b1010101 K
#3880000
0!
0'
#3885000
1!
1'
b1010110 K
#3890000
0!
0'
#3895000
1!
1'
b1010111 K
#3900000
0!
0'
#3905000
1!
1'
b1011000 K
#3910000
0!
0'
#3915000
1!
1'
b1011001 K
#3920000
0!
0'
#3925000
1!
1'
b1011010 K
#3930000
0!
0'
#3935000
1!
1'
b1011011 K
#3940000
0!
0'
#3945000
1!
1'
b1011100 K
#3950000
0!
0'
#3955000
1!
1'
b1011101 K
#3960000
0!
0'
#3965000
1!
1'
b1011110 K
#3970000
0!
0'
#3975000
1!
1'
b1011111 K
#3980000
0!
0'
#3985000
1!
1'
b1100000 K
#3990000
0!
0'
#3995000
1!
1'
b1100001 K
#4000000
0!
0'
#4005000
1!
1'
b1100010 K
#4010000
0!
0'
#4015000
1!
1'
b1100011 K
#4020000
0!
0'
#4025000
1!
1'
b0 K
#4030000
0!
0'
#4035000
1!
1'
b1 K
1I
1$
#4040000
0!
0'
#4045000
1!
1'
b10 K
#4050000
0!
0'
#4055000
1!
1'
b11 K
#4060000
0!
0'
#4065000
1!
1'
b100 K
#4070000
0!
0'
#4075000
1!
1'
b101 K
#4080000
0!
0'
#4085000
1!
1'
b110 K
#4090000
0!
0'
#4095000
1!
1'
b111 K
#4100000
0!
0'
#4105000
1!
1'
b1000 K
#4110000
0!
0'
#4115000
1!
1'
b1001 K
#4120000
0!
0'
#4125000
1!
1'
b1010 K
#4130000
0!
0'
#4135000
1!
1'
b1011 K
#4140000
0!
0'
#4145000
1!
1'
b1100 K
#4150000
0!
0'
#4155000
1!
1'
b1101 K
#4160000
0!
0'
#4165000
1!
1'
b1110 K
#4170000
0!
0'
#4175000
1!
1'
b1111 K
#4180000
0!
0'
#4185000
1!
1'
b10000 K
#4190000
0!
0'
#4195000
1!
1'
b10001 K
#4200000
0!
0'
#4205000
1!
1'
b10010 K
#4210000
0!
0'
#4215000
1!
1'
b10011 K
#4220000
0!
0'
#4225000
1!
1'
b10100 K
#4230000
0!
0'
#4235000
1!
1'
b10101 K
#4240000
0!
0'
#4245000
1!
1'
b10110 K
#4250000
0!
0'
#4255000
1!
1'
b10111 K
#4260000
0!
0'
#4265000
1!
1'
b11000 K
#4270000
0!
0'
#4275000
1!
1'
b11001 K
#4280000
0!
0'
#4285000
1!
1'
b11010 K
#4290000
0!
0'
#4295000
1!
1'
b11011 K
#4300000
0!
0'
#4305000
1!
1'
b11100 K
#4310000
0!
0'
#4315000
1!
1'
b11101 K
#4320000
0!
0'
#4325000
1!
1'
b11110 K
#4330000
0!
0'
#4335000
1!
1'
b11111 K
#4340000
0!
0'
#4345000
1!
1'
b100000 K
#4350000
0!
0'
#4355000
1!
1'
b100001 K
#4360000
0!
0'
#4365000
1!
1'
b100010 K
#4370000
0!
0'
#4375000
1!
1'
b100011 K
#4380000
0!
0'
#4385000
1!
1'
b100100 K
#4390000
0!
0'
#4395000
1!
1'
b100101 K
#4400000
0!
0'
#4405000
1!
1'
b100110 K
#4410000
0!
0'
#4415000
1!
1'
b100111 K
#4420000
0!
0'
#4425000
1!
1'
b101000 K
#4430000
0!
0'
#4435000
1!
1'
b101001 K
#4440000
0!
0'
#4445000
1!
1'
b101010 K
#4450000
0!
0'
#4455000
1!
1'
b101011 K
#4460000
0!
0'
#4465000
1!
1'
b101100 K
#4470000
0!
0'
#4475000
1!
1'
b101101 K
#4480000
0!
0'
#4485000
1!
1'
b101110 K
#4490000
0!
0'
#4495000
1!
1'
b101111 K
#4500000
0!
0'
#4505000
1!
1'
b110000 K
#4510000
0!
0'
#4515000
1!
1'
b110001 K
#4520000
0!
0'
#4525000
1!
1'
b110010 K
#4530000
0!
0'
#4535000
1!
1'
b110011 K
0I
0$
#4540000
0!
0'
#4545000
1!
1'
b110100 K
#4550000
0!
0'
#4555000
1!
1'
b110101 K
#4560000
0!
0'
#4565000
1!
1'
b110110 K
#4570000
0!
0'
#4575000
1!
1'
b110111 K
#4580000
0!
0'
#4585000
1!
1'
b111000 K
#4590000
0!
0'
#4595000
1!
1'
b111001 K
#4600000
0!
0'
#4605000
1!
1'
b111010 K
#4610000
0!
0'
#4615000
1!
1'
b111011 K
#4620000
0!
0'
#4625000
1!
1'
b111100 K
#4630000
0!
0'
#4635000
1!
1'
b111101 K
#4640000
0!
0'
#4645000
1!
1'
b111110 K
#4650000
0!
0'
